Workbook

Sheet Parameter Categories
A1: Category | B1: Parameter | C1: Description | D1: Data Source | E1: Data Type | F1: Material | G1: Element
A2: 1. Identification and General Information | B2: Product Name | C2: Name of the material | D2: Manufacturer documentation | E2: Text | F2: x | G2: x
B3: Product ID | C3: Unique identifier of the material | D3: Certification or compliance report | E3: String | F3: x | G3: x
B4: Product Image | C4: Image of material in PNG | D4: Manufacturer documentation | E4: Image | F4: x
B5: Object number | C5: Unique BIM-generated object reference | D5: BIM parameter | E5: String | F5: x | G5: x
B6: Material Type | C6: Category or type of material | D6: BIM parameter | E6: Text | F6: x | G6: x
B7: Manufacturer | C7: Producer of the material | D7: Manufacturer documentation | E7: Text | F7: x | G7: x
B8: Link Manufacturer | C8: URL to manufacturer page | D8: Manufacturer documentation | E8: String | F8: x | G8: x
B9: Distributor | C9: Name and contact of distributor | D9: Manufacturer documentation | E9: Text | F9: x
B10: Link Distributor | C10: URL to distributor page | D10: Distributor documentation | E10: String | F10: x
B11: Supplier | C11: Name and contact of supplier or sub-supplier | D11: Manufacturer documentation | E11: Text | F11: x
B12: Link Supplier | C12: URL to supplier page | D12: Supplier documentation | E12: String | F12: x
B13: Transportation Route | C13: Typical transport routes and modes | D13: Manufacturer documentation | E13: Text | F13: x
B14: Traceability ID | C14: Unique digital ID for traceability (QR or blockchain) | D14: Manufacturer documentation | E14: String | F14: x | G14: x
B15: Origin | C15: Geographic source product | D15: Manufacturer documentation | E15: Text | F15: x | G15: x
B16: Version number | C16: Passport version control | D16: Assigned | E16: String | F16: x | G16: x
A17: 2. Physical and Technical Properties | B17: Material | C17: Description of the material | D17: Manufacturer documentation | E17: Text | F17: x
B18: Component | C18: Description of the component | D18: Manufacturer documentation | E18: Text | G18: x
B19: Composition | C19: Material composition and proportions | D19: Manufacturer documentation | E19: Text | F19: x | G19: x
B20: Dimensions | C20: Dimention type (cm) | D20: Manufacturer documentation | E20: Text | F20: x | G20: x
B21: Height | C21: Height of the material (mm) | D21: BIM parameter | E21: Numeric | F21: x | G21: x
B22: Length | C22: Length of the material (mm) | D22: BIM parameter | E22: Numeric | F22: x | G22: x
B23: Width | C23: Width of the material (mm) | D23: BIM parameter | E23: Numeric | F23: x | G23: x
B24: Volume | C24: Volume of the material(m³) | D24: Manufacturer documentation | E24: Numeric | F24: x | G24: x
B25: Dry density | C25: Mass per unit volume completely oven-dried (kg/m³) | D25: Manufacturer documentation | E25: Numeric | F25: x | G25: x
B26: Equilibrium density | C26: Mass per unit volume on normal ambient conditions (kg/m³) | D26: Manufacturer documentation | E26: Numeric | F26: x | G26: x
B27: Weight | C27: Mass per unit (kg) | D27: Manufacturer documentation | E27: Numeric | F27: x | G27: x
B28: Compressive strength | C28: Compressive resistance (Mpa) | D28: Laboratory test | E28: Numeric | F28: x | G28: x
B29: Shear strength | C29: Flextural resistance (Mpa) | D29: Laboratory test | E29: Numeric | F29: x | G29: x
B30: Thermal conductivity | C30: λ-value (W/mK) | D30: Laboratory test | E30: Numeric | G30: x
B31: Heat transfer coefficient | C31: u-value (W/m²K) | D31: Laboratory test | E31: Numeric | G31: x
B32: Sprecific heat capacity | C32: Heat required to raise temperature (J/kg·K) | D32: Laboratory test | E32: Numeric | G32: x
B33: Phase shift | C33: Delay in heat transfer through material (hours) | D33: Laboratory test | E33: Numeric | G33: x
B34: Moisture Buffer Value | C34: Moisture absorption/desorption capacity of the material | D34: Laboratory test | E34: Numeric | G34: x
B35: Water vapour diffusion resistance when wet | C35: Ability of material to allow vapor to pass through | D35: Laboratory test | E35: Numeric | F35: x | G35: x
B36: Water vapour diffusion resistance when dry | C36: Ability of material to allow vapor to pass through | D36: Laboratory test | E36: Numeric | F36: x | G36: x
B37: Water vapour absorption resistance | C37: Resistance to vapor absorption at surface | D37: Laboratory test | E37: Numeric | F37: x | G37: x
B38: Standard compliance | C38: Of relevant building or environmental standards | D38: Certification or compliance report | E38: Boolean | F38: x | G38: x
A39: 3. Circularity and End-of-Life Information | B39: Connection Type | C39: Type of material connection (Dry interlock / bolted / screwed; Mortar / adhesive / binder-based; Cast-in-place) | D39: Manufacturer documentation | E39: Text | G39: x
B40: Connection Score | C40: Ease of separation or reversibility score | D40: Assigned | E40: Numeric | G40: x
B41: Prefabrication | C41: If product is prefabricated | D41: Manufacturer documentation | E41: Boolean | F41: x | G41: x
B42: Prefabrication factor | C42: Proportion of prefabricated components | D42: Assigned | E42: Numeric | F42: x | G42: x
B43: Deconstructability score | C43: Ease of disassembly and recovery at end of life (simplified from Atta) | D43: Calculated | E43: Numeric | F43: x | G43: x
B44: Recycling potential | C44: % of material recyclable | D44: Manufacturer documentation | E44: Numeric | F44: x | G44: x
B45: Reusability | C45: If material is reusable as-is | D45: Manufacturer documentation | E45: Boolean | F45: x | G45: x
B46: Reusability potential | C46: Likelihood of reuse without processing | D46: Manufacturer documentation | E46: Numeric | F46: x | G46: x
B47: Recovery score | C47: Ratio of reusable, recyclable, non-toxic, uncoated elements (simplified from Atta) | D47: Calculated | E47: Numeric | F47: x | G47: x
B48: Disassembly potential | C48: Disassembly feasibility index | D48: Assigned | E48: Numeric | F48: x | G48: x
B49: Disassembly instructions | C49: Guidelines for separation or dismantling | D49: Manufacturer documentation | E49: Text | F49: x | G49: x
B50: Secondary use scenarios | C50: Possible post-use applications | D50: Manufacturer documentation | E50: Text | F50: x | G50: x
B51: End-of-life recommendation | C51: Suggested disposal or reuse pathway | D51: Manufacturer documentation | E51: Text | F51: x | G51: x
A52: 4. Environmental Performance and LCA Data | B52: EPD | C52: Developed recent Environmental Product Declaration | D52: Manufacturer documentation | E52: Boolean | F52: x | G52: x
B53: Link EPD | C53: URL to Environmental Product Declaration | D53: Manufacturer documentation | E53: Link | F53: x | G53: x
B54: Global Warming Potential (GWP) | C54: CO₂ equivalent per unit (All stages) | D54: EPD | E54: Numeric | F54: x | G54: x
B55: Primary Energy Intensity (PEI) | C55: Total MJ consumed during production per unit (All stages) | D55: EPD | E55: Numeric | F55: x | G55: x
B56: Primary Energy Intensity (PERT) Renewable | C56: Renewable MJ consumed during production per unit (All stages) | D56: EPD | E56: Numeric | F56: x | G56: x
B57: Primary Energy Intensity (PENRT) Non-renewable | C57: Non-renewable MJ consumed during production per unit (All stages) | D57: EPD | E57: Numeric | F57: x | G57: x
B58: Acidification Potential (AP) | C58: SO₂ equivalent per unit (All stages) | D58: EPD | E58: Numeric | F58: x | G58: x
B59: Embodied carbon | C59: Total CO₂ eq. Per kg for manufacturing (A-stage) | D59: EPD | E59: Numeric | F59: x | G59: x
B60: Biogenic carbon storage | C60: CO₂ sequestered in bio-based material | D60: EPD | E60: Numeric | F60: x | G60: x
B61: End-of-life emissions | C61: Emissions at disposal or biodegradation stage CO₂ eq. Per kg or m2 (C/D-stage) | D61: EPD | E61: Numeric | F61: x | G61: x
B62: Circularity index | C62: Composite score combining reuse and recycling ratios | D62: Calculated | E62: Numeric | F62: x | G62: x
B63: Normalized environmental performance | C63: Environmental impact normalized against reference values | D63: Calculated | E63: Numeric | F63: x | G63: x
B64: Secondary life weighting | C64: Weighted environmental effect for second-life use | D64: Calculated | E64: Numeric | F64: x | G64: x
B65: Environmental score | C65: Normalized overall impact (simplified from Atta) | D65: Calculated | E65: Numeric | F65: x | G65: x
A66: 5. Condition, Maintenance, and Temporal Data | B66: Service life | C66: Expected durability or usable lifespan | D66: Manufacturer documentation | E66: Numeric | F66: x | G66: x
B67: Mantenance Instructions | C67: Guidelines for maintaining the product | D67: Manufacturer documentation | E67: Text | F67: x
B68: Soursing distance | C68: Distance of tavel of sourcing for production | D68: Manufacturer documentation | E68: Numeric | F68: x | G68: x
B69: Warranty | C69: If warranty applies | D69: Manufacturer documentation | E69: Text | F69: x | G69: x
B70: Warranty duration | C70: Duration of warranty (Months) | D70: Manufacturer documentation | E70: Numeric | F70: x | G70: x
B71: Update history | C71: Log of changes or inspections | D71: Auto-generated (BIM) | E71: Log | F71: x | G71: x
A72: 6. Safety and Compliance | B72: HPD | C72: Developed recent Environmental Product Declaration | D72: Manufacturer documentation | E72: Boolean | F72: x | G72: x
B73: Link HPD | C73: URL to Environmental Product Declaration | D73: Manufacturer documentation | E73: Link | F73: x | G73: x
B74: Hazard classification | C74: Identifies presence of hazardous components | D74: Manufacturer documentation | E74: Text | F74: x | G74: x
B75: PM | C75: Potential occurrence of diseases due to particulate matter emissions; | D75: Manufacturer documentation | E75: Numeric | F75: x | G75: x
B76: IRP | C76: Potential effect from human exposure to U235 | D76: Manufacturer documentation | E76: Numeric | F76: x | G76: x
B77: ETP-fw | C77: Potential Ecosystem toxicity comparator unit | D77: Manufacturer documentation | E77: Numeric | F77: x | G77: x
B78: HTP-c | C78: Potential human toxicity comparator unit - carcinogenic effect | D78: Manufacturer documentation | E78: Numeric | F78: x | G78: x
B79: HTP-nc | C79: Potential human toxicity comparator unit - non-carcinogenic effect | D79: Manufacturer documentation | E79: Numeric | F79: x | G79: x
B80: SQP | C80: Potential soil quality index | D80: Manufacturer documentation | E80: Numeric | F80: x | G80: x
B81: Toxicity | C81: Presence of harmful compounds or emissions | D81: Manufacturer documentation | E81: Boolean | F81: x | G81: x
B82: Class | C82: Safety class according to relevant standard | D82: Safety datasheet | E82: Text | F82: x | G82: x
B83: s-subclass | C83: Specific subclass | D83: Safety datasheet | E83: Text | F83: x | G83: x
B84: d_subclass | C84: Detailed subclass | D84: Safety datasheet | E84: Text | F84: x | G84: x
... B87: Coatings or treatments | C87: Surface finishes or chemical treatments | D87: Manufacturer documentation | E87: Text | F87: x | G87: x
B88: PPE requirements | C88: Recommended protective equipment | D88: Manufacturer documentation | E88: Text | G88: x
B89: Compliance certificates | C89: If theres health, safety, or environmental certifications | D89: Manufacturer documentation | E89: Boolean | F89: x | G89: x
A90: 7. Cultural and Sensory Information | B90: Sound Absorption Coefficient | C90: Fraction of incident sound absorbed by the material | D90: Laboratory test | E90: Numeric | G90: x
B91: Sound Attenuation Index | C91: Reduction in sound transmission through material (Rw) | D91: Laboratory test | E91: Numeric | G91: x
B92: Color | C92: Color of the material | D92: Direct observation | E92: Text | F92: x
B93: Odor | C93: Scent of the material | D93: Direct observation | E93: Text | F93: x
B94: Texture | C94: Texture of the material | D94: Direct observation | E94: Text | F94: x
B95: Temperature to touch | C95: Surface temperature of the material | D95: Direct observation | E95: Text | F95: x
B96: Climate Suitability | C96: Appropriateness of the material for local weather conditions | D96: Literature / Regional study | E96: Text / Numeric | F96: x
B97: Agriculatural Value | C97: Material’s relevance or contribution to farming or land use | D97: Literature / Regional study | E97: Text / Numeric | F97: x
B98: Resourse Availability | C98: Ease of obtaining the material in a given region | D98: Literature / Regional study | E98: Text / Numeric | F98: x
B99: Material Aging | C99: How the material changes in appearance and performance over time | D99: Literature / Expert evaluation | E99: Text / Numeric | F99: x
B100: Architectural Expression | C100: How the material conveys style, form, or design intent | D100: Literature / Expert evaluation | E100: Text / Numeric | F100: x
B101: Aesthetic Narratives | C101: Visual or sensory stories the material communicates | D101: Literature / Expert evaluation | E101: Text / Numeric | F101: x | G101: x
B102: Thermal Comfort | C102: Perceived comfort due to heat exchange with surroundings | D102: Literature / User experience | E102: Text / Numeric | G102: x
...

Sheet Shared parameters
A1: Parameter | B1: Name | C1: Group | D1: Data Type
A2: =INDEX(Categories[Parameter],ROW(B1)) -> Product Name | B2: DPP_AUT_Name | C2: AUT_Authoring | D2: Text
A3: =INDEX(Categories[Parameter],ROW(B2)) -> Product ID | B3: DPP_AUT_ID | C3: AUT_Authoring | D3: Text
A4: =INDEX(Categories[Parameter],ROW(B3)) -> Product Image | B4: DPP_AUT_Image | C4: AUT_Authoring | D4: Image
A5: =INDEX(Categories[Parameter],ROW(B4)) -> Object number | B5: DPP_AUT_GUID | C5: AUT_Authoring | D5: Text
A6: =INDEX(Categories[Parameter],ROW(B5)) -> Material Type | B6: DPP_AUT_MaterialType | C6: AUT_Authoring | D6: Text
A7: =INDEX(Categories[Parameter],ROW(B6)) -> Manufacturer | B7: DPP_AUT_Manufacturer | C7: AUT_Authoring | D7: Text
A8: =INDEX(Categories[Parameter],ROW(B7)) -> Link Manufacturer | B8: DPP_AUT_Manufacturer_URL | C8: AUT_Authoring | D8: URL
A9: =INDEX(Categories[Parameter],ROW(B8)) -> Distributor | B9: DPP_AUT_Distribuitor | C9: AUT_Authoring | D9: Text
A10: =INDEX(Categories[Parameter],ROW(B9)) -> Link Distributor | B10: DPP_AUT_Distribuitor_URL | C10: AUT_Authoring | D10: URL
A11: =INDEX(Categories[Parameter],ROW(B10)) -> Supplier | B11: DPP_AUR_Supplier | C11: AUT_Authoring | D11: Text
A12: =INDEX(Categories[Parameter],ROW(B11)) -> Link Supplier | B12: DPP_AUR_Supplier_URL | C12: AUT_Authoring | D12: URL
A13: =INDEX(Categories[Parameter],ROW(B12)) -> Transportation Route | B13: DPP_AUT_TransRoute | C13: AUT_Authoring | D13: Multiline Text
... A117: =INDEX(Categories[Parameter],ROW(B116)) -> Lifecycle cost estimate | B117: DPP_COD_LCC_EUR | C117: COD_CostData | D117: Cost per area

Sheet Built In Parameter groups
A1: Group parameter Under Names | B1: Revit API name | C1: BP Group | D1: Type | E1: Definition
A2: Analysis Results | B2: Analysis Results | C2: PG_ANALYSIS_RESULTS | D2: Analysis & Analytical Groups | E2: For displaying calculated values (e.g., structural or energy analysis outputs)
A3: Analytical Alignment | B3: AnalyticalAlignment | C3: PG_ALIGNMENT | D3: Analysis & Analytical Groups | E3: For parameters defining analytical model alignment or adjustments
A4: Analytical Model | B4: AnalyticalModel | C4: PG_ANALYTICAL_MODEL | D4: Analysis & Analytical Groups | E4: For parameters related to analytical representation of physical elements
A5: Constraints | B5: Constraints | C5: PG_CONSTRAINTS | D5: Construction & Constraints | E5: For controlling element relationships (e.g., levels, offsets, locked dimensions)
A6: Construction | B6: Construction | C6: PG_CONSTRUCTION | D6: Construction & Constraints | E6: For parameters related to construction sequencing, methods, or materials
A7: Data | B7: Data | C7: PG_DATA | D7: Data & Geometry | E7: General-purpose data parameters (e.g., IDs, classification codes)
A8: Dimensions | B8: Geometry | C8: PG_DIMENSIONS | D8: Data & Geometry | E8: For numeric or size parameters (height, width, depth, etc.)
A9: Division Geometry | B9: DivisionGeometry | C9: PG_GEOMETRY | D9: Data & Geometry | E9: For subdivision or geometry-based controls, typically used in civil/landscape or curtain systems
A10: Electrical | B10: Electrical | C10: PG_ELECTRICAL | D10: Electrical | E10: General electrical parameters (e.g., voltage, panel, circuit)
A11: Electrical - Circuiting | B11: ElectricalCircuiting | C11: PG_CIRCUITING | D11: Electrical | E11: Circuit connection parameters (load classification, circuit number)
A12: Electrical - Lighting | B12: ElectricalLighting | C12: PG_LIGHTING | D12: Electrical | E12: For light fixtures, wattage, illumination levels
... A52: Visualization | B52: Visualization | C52: PG_VISUALIZATION | D52: Documentation & Text | E52: For rendering or appearance settings

Sheet Data Entry
A1: Parameter | B1: Data | C1: Unit | D1: Range | E1: Source | F1: Formulas
A2: =+INDEX(Categories[Parameter],ROW(B1)) -> Product Name | B2: Hempstone | C2: — | D2: — | E2: Technical data sheet 06/2025
A3: =+INDEX(Categories[Parameter],ROW(B2)) -> Product ID | B3: Z-17.25-1299 | C3: ID | D3: — | E3: German general type approval
A4: =+INDEX(Categories[Parameter],ROW(B3)) -> Product Image | B4: ..\..\werner schönthaler\hanfsteine Sch├Ânthaler Kopie.png | C4: — | D4: — | E4: Sent by Manufacturer
A5: =+INDEX(Categories[Parameter],ROW(B4)) -> Object number | C5: GUID | D5: — | E5: BIM parameter
A6: =+INDEX(Categories[Parameter],ROW(B5)) -> Material Type | B6: Type II | C6: — | D6: Type I (Ingredients); Type II (Modular); Type III (Sub-Components) | E6: Waterman materials passport framework 2023
A7: =+INDEX(Categories[Parameter],ROW(B6)) -> Manufacturer | B7: Schönthaler Bausteinwerk GmbH | C7: — | D7: — | E7: German general type approval
A8: =+INDEX(Categories[Parameter],ROW(B7)) -> Link Manufacturer | B8: https://www.hanfstein.eu/ | C8: — | D8: — | E8: Sent by Manufacturer
A9: =+INDEX(Categories[Parameter],ROW(B8)) -> Distributor | B9: NA | C9: — | D9: NA
A10: =+INDEX(Categories[Parameter],ROW(B9)) -> Link Distributor | B10: NA | C10: — | D10: NA
A11: =+INDEX(Categories[Parameter],ROW(B10)) -> Supplier | B11: NA | C11: — | D11: NA
A12: =+INDEX(Categories[Parameter],ROW(B11)) -> Link Supplier | B12: NA | C12: — | D12: NA
A13: =+INDEX(Categories[Parameter],ROW(B12)) -> Transportation Route
A14: =+INDEX(Categories[Parameter],ROW(B13)) -> Traceability ID | B14: a1b2c3d4-e5f6-7890-1234-567890abcdef | C14: QR | D14: QR-RFID-NFC-Serial number | E14: Example of a QR code string
A15: =+INDEX(Categories[Parameter],ROW(B14)) -> Origin | B15: 39020 Oris (BZ) | C15: — | D15: — | E15: German general type approval
A16: =+INDEX(Categories[Parameter],ROW(B15)) -> Version number | B16: HKZ 335 | C16: No. | D16: HKZ 335 - HKZ 360 | E16: Assigned
A17: =+INDEX(Categories[Parameter],ROW(B16)) -> Material | B17: Infill masonry made of hemp stones | C17: — | D17: — | E17: BIM parameter
A18: =+INDEX(Categories[Parameter],ROW(B17)) -> Component | B18: 8 hempstone bricks of 8x50x20 with a 1/3 displacement with hemp-lime mortar | C18: — | D18: —
A19: =+INDEX(Categories[Parameter],ROW(B18)) -> Composition | B19: Hemp-lime composite | C19: — | D19: Hemp-clay; Hemp-cement; Hemp-biopolymer; Hemp-MgO | E19: Technical data sheet 06/2025 (Range by Steyn et al., 2025; Barbhuiya & Bhusan, 2022)
A20: =+INDEX(Categories[Parameter],ROW(B19)) -> Dimensions | B20: 8x50x20 | C20: cm | D20: 6x22x11; 8x50x20; 12x55x20; 15x50x20; 20x55x20; 24x55x20; 38x55x20; 44x55x20 | E20: Technical data sheet 2017
A21: =+INDEX(Categories[Parameter],ROW(B20)) -> Height | B21: 200 | C21: mm | D21: 200 - 300 | E21: BIM parameter (Range by standard masonry formats)
A22: =+INDEX(Categories[Parameter],ROW(B21)) -> Length | B22: 80 | C22: mm | D22: 100 - 250 | E22: BIM parameter (Range by standard masonry formats)
A23: =+INDEX(Categories[Parameter],ROW(B22)) -> Width | B23: 500 | C23: mm | D23: 300 - 600 | E23: BIM parameter (Range by standard masonry formats)
A24: =+INDEX(Categories[Parameter],ROW(B23)) -> Volume | B24: 0.008 | C24: — | D24: 0.006 - 0.036 | E24: Calculated | F24: Height*Lenght*Width
A25: =+INDEX(Categories[Parameter],ROW(B24)) -> Dry density | B25: 335 | C25: kg/m³ | D25: 310-360 | E25: EPD 2025
A26: =+INDEX(Categories[Parameter],ROW(B25)) -> Equilibrium density | B26: 405 | C26: kg/m³ | D26: 390-450 | E26: EPD 2025
A27: =+INDEX(Categories[Parameter],ROW(B26)) -> Weight | B27: 2.68 | C27: Kg | D27: 6.00 - 15.00 | E27: Calculated | F27: Volume*Dry density
A28: =+INDEX(Categories[Parameter],ROW(B27)) -> Compressive strength | B28: 0.5 | C28: Mpa | D28: 0.06-0.8 | E28: Technical data sheet 06/2025 (Range by Steyn et al., 2025; Asghari & Memari, 2024)
A29: =+INDEX(Categories[Parameter],ROW(B28)) -> Shear strength | B29: 0.12 | C29: Mpa | D29: 0.08-0.15 | E29: Hempblock brochure (Range by Steyn et al., 2025; Brzyski et al., 2020)
A30: =+INDEX(Categories[Parameter],ROW(B29)) -> Thermal conductivity | B30: 0.07 | C30: W/(mK) | D30: 0.05-0.22 | E30: Technical data sheet 06/2025 (Range by Collet & Pretot in Steyn et al., 2025)
A31: =+INDEX(Categories[Parameter],ROW(B30)) -> Heat transfer coefficient | B31: 0.76 | C31: W/(m²K) | D31: 0.15-0.76 | E31: Technical data sheet 06/2025
A32: =+INDEX(Categories[Parameter],ROW(B31)) -> Sprecific heat capacity | B32: 1870 | C32: (J/kg.K) | E32: Technical data sheet 06/2025
A33: =+INDEX(Categories[Parameter],ROW(B32)) -> Phase shift | B33: 0.13125 | C33: Hours | D33: 3:09-24:30 | E33: Technical data sheet 06/2025
A34: =+INDEX(Categories[Parameter],ROW(B33)) -> Moisture Buffer Value | B34: 2.35 | C34: g/m²%HR | D34: 0-2.5 | E34: Technical data sheet 2017
A35: =+INDEX(Categories[Parameter],ROW(B34)) -> Water vapour diffusion resistance when wet | B35: 3.8 | C35: μ | D35: 4.9 - 5.7 | E35: Technical data sheet 06/2025 (Range by Brzyski et al., 2020)
A36: =+INDEX(Categories[Parameter],ROW(B35)) -> Water vapour diffusion resistance when dry | B36: 4.3 | C36: μ | D36: 12.2 - 12.4 | E36: Technical data sheet 06/2025 (Range by Brzyski et al., 2020)
A37: =+INDEX(Categories[Parameter],ROW(B36)) -> Water vapour absorption resistance | B37: 19 | C37: d[g/m²vh] | D37: — | E37: Technical data sheet 06/2025
A38: =+INDEX(Categories[Parameter],ROW(B37)) -> Standard compliance | B38: Yes | C38: — | D38: Yes/No | E38: German general type approval
A39: =+INDEX(Categories[Parameter],ROW(B38)) -> Connection Type | B39: Mortar | C39: — | D39: Dry interlock / bolted / screwed; Mortar / adhesive / binder-based; Cast-in-place | E39: https://www.hanfstein.eu/en/application/
A40: =+INDEX(Categories[Parameter],ROW(B39)) -> Connection Score | B40: 0.3 | C40: Score | D40: 0.0 (easy) - 1.0 (hard) | E40: Assigned
A41: =+INDEX(Categories[Parameter],ROW(B40)) -> Prefabrication | B41: Yes | C41: — | D41: Yes/No | E41: Report for KBOB list
A42: =+INDEX(Categories[Parameter],ROW(B41)) -> Prefabrication factor | B42: 1 | C42: Score | D42: 1 (Yes) - 0 (No) | E42: Range Atta et al. 2021 | F42: if(Prefabrication,1,0)
A43: =+INDEX(Categories[Parameter],ROW(B42)) -> Deconstructability score | B43: 0.5 | C43: Score | D43: 0.0-1.0 | E43: Range Atta et al. 2021 | F43: ConnectionScore+PrefabricationFactor/2
A44: =+INDEX(Categories[Parameter],ROW(B43)) -> Recycling potential | B44: 100 | C44: % | D44: 1-100% | E44: Technical data sheet 2017
A45: =+INDEX(Categories[Parameter],ROW(B44)) -> Reusability | B45: No | C45: — | D45: Yes/No | E45: EPD 2025
A46: =+INDEX(Categories[Parameter],ROW(B45)) -> Reusability potential | B46: 0 | C46: Score | D46: 0-1 | E46: Range Atta et al. 2021 | F46: if(Reusability,1,0)
A47: =+INDEX(Categories[Parameter],ROW(B46)) -> Recovery score | B47: 0.5 | C47: Score | D47: 0.0-1.0 | E47: Range Atta et al. 2021 | F47: ((RecyclingPotential/100)+ReusabilityPotential+(if(Toxicity,0,1))+(if(Coatings,0,1)))/4
A48: =+INDEX(Categories[Parameter],ROW(B47)) -> Disassembly potential | B48: 3 | C48: Score | D48: 1 (Dificult)- 2 (Moderate)- 3 (Easy) | E48: Range assigned
A49: =+INDEX(Categories[Parameter],ROW(B48)) -> Disassembly instructions | B49: Mechanical dismantling: Crushing and Sieving for Recycling | C49: — | D49: Manual dismantling; Semi-Mechanical Disassembly; Thermal Disassembly; Chemical Disassembly; Demolition; Modular Disassembly | E49: EPD 2025 (Range by ISO 20887:2020)
A50: =+INDEX(Categories[Parameter],ROW(B49)) -> Secondary use scenarios | B50: Reused on the construction site for applications requiring increased density, such as floor material | C50: — | D50: Direc reuse; Partial reuse; Reprocessing into aggregare; Soil amendment; Upcycling into thermal or acoustic insulation; Upcycling into new composites or panels; Backfilling | E50: EPD 2025 (Range by European Commission 2020, LEVEL(s))
A51: =+INDEX(Categories[Parameter],ROW(B50)) -> End-of-life recommendation | B51: Composting and soil improvement; Disposal via incineration | C51: — | D51: Biological recovery; Material recyclcing; Energy recovery; Landfill disposal | E51: EPD 2025 (Range by EN 15804:2012 +A2:2019)
A52: =+INDEX(Categories[Parameter],ROW(B51)) -> EPD | B52: Yes | C52: — | D52: Yes/No | E52: By manufacturer
A53: =+INDEX(Categories[Parameter],ROW(B52)) -> Link EPD | B53: https://www.bau-epd.at/epd/data/schoenthaler-bausteinwerk-gmbh-hanfsteine-ecoinvent-2025 | C53: URL | D53: — | E53: By manufacturer
A54: =+INDEX(Categories[Parameter],ROW(B53)) -> Global Warming Potential (GWP) | B54: 1.3392 | C54: kg CO₂eq./ Block | D54: -6.6 - 3.8 | E54: Calculated from EPD (Range derived from published volumetric ranges (≈ −184 to +105 kg CO₂e/m³)) | F54: 167.4*Volume
A55: =+INDEX(Categories[Parameter],ROW(B54)) -> Primary Energy Intensity (PEI)
A56: =+INDEX(Categories[Parameter],ROW(B55)) -> Primary Energy Intensity (PERT) Renewable | B56: 18.40872 | C56: MJ | D56: 10 - 30 | E56: Calculated from EPD (Range corresponds to ≈ 2.5 – 3.5 MJ/kg embodied energy for densities of 300–330 kg/m3) | F56: 2301.09*Volume
A57: =+INDEX(Categories[Parameter],ROW(B56)) -> Primary Energy Intensity (PENRT) Non-renewable | B57: 17.02688 | C57: MJ | D57: 8 - 25 | E57: Calculated from EPD (Range corresponds to ≈ 2.5 – 3.5 MJ/kg embodied energy for densities of 300–330 kg/m3) | F57: 2128.36*Volume
A58: =+INDEX(Categories[Parameter],ROW(B57)) -> Acidification Potential (AP) | B58: 0.00024935 | C58: kg SO₂ eq. | D58: 0.0001 - 0.0006 | E58: Calculated from EPD (Rage based on reported values of 74–143 g SO₂ eq./m² of wall scaled to typical hempcrete block volumes) | F58: 167.4*Volume
A59: =+INDEX(Categories[Parameter],ROW(B58)) -> Embodied carbon | B59: -1.744 | C59: kg CO₂eq./ Block | D59: -2.5 - 2.0 | E59: Calculated from EPD (Range based on based on published LCAs of hempcrete walls and prefabricated blocks in the UK, France, and Italy) | F59: 218*Volume
A60: =+INDEX(Categories[Parameter],ROW(B59)) -> Biogenic carbon storage | B60: 0.4488 | C60: kg CO₂eq./ Block | D60: 0.2 - 0.8 | E60: Calculated from EPD (Range based on studies quantifying carbon sequestration through photosynthesis and lime carbonation) | F60: 56.1*Volume
A61: =+INDEX(Categories[Parameter],ROW(B60)) -> End-of-life emissions | B61: 1.7772 | C61: kg CO₂eq./ Block | D61: 1.0 - 2.5 | E61: Calculated from EPD (Range based on scenarios assuming incineration, composting, or partial mineralization at disposal) | F61: 222.15*Volume
A62: =+INDEX(Categories[Parameter],ROW(B61)) -> Circularity index | B62: 70 | C62: % | D62: 0-100 | E62: Range assigned
A63: =+INDEX(Categories[Parameter],ROW(B62)) -> Normalized environmental performance | B63: 0.992 | C63: Score | D63: 0.0-1.0 | E63: Range Atta et al. 2021 | F63: Ei=1-(GWP/167.4)
A64: =+INDEX(Categories[Parameter],ROW(B63)) -> Secondary life weighting | B64: 0.75 | C64: Score | D64: 0.0-1.0 | E64: Range Atta et al. 2021 | F64: W=RecoveryScore*(1-0.5)+0.5
A65: =+INDEX(Categories[Parameter],ROW(B64)) -> Environmental score | B65: 0.744 | C65: Score | D65: 0.0-1.0 | E65: Range Atta et al. 2021 | F65: Ei*w
A66: =+INDEX(Categories[Parameter],ROW(B65)) -> Service life | B66: 100 | C66: years | D66: 100 - 300 | E66: Technical data sheet 06/2025 (Expected real lifespan under proper maintenance and protection: coatings, controlled RH < 70%)
A67: =+INDEX(Categories[Parameter],ROW(B66)) -> Mantenance Instructions
A68: =+INDEX(Categories[Parameter],ROW(B67)) -> Soursing distance | B68: <500 | C68: km | D68: < 100 - 500 | E68: By manufacturer (Benchmark of regional or local soursing in some PCRs)
A69: =+INDEX(Categories[Parameter],ROW(B68)) -> Warranty | B69: No | C69: — | D69: Yes/No | E69: By manufacturer
A70: =+INDEX(Categories[Parameter],ROW(B69)) -> Warranty duration | B70: 0 | C70: — | E70: NA
A71: =+INDEX(Categories[Parameter],ROW(B70)) -> Update history | C71: Date | D71: —
A72: =+INDEX(Categories[Parameter],ROW(B71)) -> HPD | B72: No | C72: — | D72: Yes/No | E72: By manufacturer
A73: =+INDEX(Categories[Parameter],ROW(B72)) -> Link HPD | B73: — | C73: URL | D73: — | E73: By manufacturer
A74: =+INDEX(Categories[Parameter],ROW(B73)) -> Hazard classification | B74: Not classified as hazardous | C74: — | D74: Category 1- 4 | E74: Technical data sheet 06/2025 (Range GHS)
A75: =+INDEX(Categories[Parameter],ROW(B74)) -> PM | B75: 2.272e-07 | C75: CTUh per block | D75: 1.0E-7 - 5.0E-7 | E75: EPD 2025 (Total stages A1-A5+ C1-C3+ D) (Range based on comparative LCAs and EPD datasets of hemp-lime wall systems and other bio-based materials) | F75: (0.0000284)*Volume
A76: =+INDEX(Categories[Parameter],ROW(B75)) -> IRP | B76: 0.01624 | C76: kBq U-235 eq per block | D76: 0.01 - 0.05 | E76: EPD 2025 (Total stages A1-A5+ C1-C3+ D) (Range based on comparative LCAs and EPD datasets of hemp-lime wall systems and other bio-based materials) | F76: (2.03)*Volume
A77: =+INDEX(Categories[Parameter],ROW(B76)) -> ETP-fw | B77: 12.266568 | C77: CTUe (Block) | D77: 8 - 20 | E77: EPD 2025 (Total stages A1-A5+ C1-C3+ D) (Range based on comparative LCAs and EPD datasets of hemp-lime wall systems and other bio-based materials) | F77: (1533.321)*Volume
A78: =+INDEX(Categories[Parameter],ROW(B77)) -> HTP-c | B78: 7.070848e-10 | C78: CTUh (Block) | D78: 1.0E-10 - 1.0E-9 | E78: EPD 2025 (Total stages A1-A5+ C1-C3+ D) (Range based on comparative LCAs and EPD datasets of hemp-lime wall systems and other bio-based materials) | F78: (0.0000000883856)*Volume
A79: =+INDEX(Categories[Parameter],ROW(B78)) -> HTP-nc | B79: 2.309336e-08 | C79: CTUh (Block) | D79: 1.0E-8 - 1.0E-7 | E79: EPD 2025 (Total stages A1-A5+ C1-C3+ D) (Range based on comparative LCAs and EPD datasets of hemp-lime wall systems and other bio-based materials) | F79: (0.00000288667)*Volume
A80: =+INDEX(Categories[Parameter],ROW(B79)) -> SQP | B80: 62.72 | C80: — | D80: 40 - 90 | E80: EPD 2025 (Total stages A1-A5+ C1-C3+ D) (Range based on comparative LCAs and EPD datasets of hemp-lime wall systems and other bio-based materials) | F80: (7840)*Volume
A81: =+INDEX(Categories[Parameter],ROW(B80)) -> Toxicity | B81: No | C81: — | D81: Yes/No | E81: Technical data sheet 06/2025
A82: =+INDEX(Categories[Parameter],ROW(B81)) -> Class | B82: B (Very limited contribution to fire) | C82: — | D82: A-F (Non combustible to No performance determined) | E82: Technical data sheet 06/2025 (Range DIN EN 13501-1)
A83: =+INDEX(Categories[Parameter],ROW(B82)) -> s-subclass | B83: s1 (Little or no smoke) | C83: — | D83: s1-s3 (Little or no smoke to Hight smoke prodcution) | E83: Technical data sheet 06/2025 (Range DIN EN 13501-1)
A84: =+INDEX(Categories[Parameter],ROW(B83)) -> d_subclass | B84: d0 (No flaming droplets or particles) | C84: — | D84: d0-d2 (No to significante flaming droplets or particles) | E84: Technical data sheet 06/2025 (Range DIN EN 13501-1)
A85: =+INDEX(Categories[Parameter],ROW(B84)) -> Fire resistance | B85: B-s1; d0 | C85: — | D85: A1;A2-s1,d0;A2-s3,d2;B-s1,d0;B-s3,d2;C-s1,d0;C-s3,d2;D-s1,d0;D-s3,d2;E-d2;F | E85: Technical data sheet 06/2025 (Range DIN EN 13501-1)
A86: =+INDEX(Categories[Parameter],ROW(B85)) -> Coatings | B86: Yes | C86: — | D86: Yes/No | E86: Technical data sheet 06/2025
A87: =+INDEX(Categories[Parameter],ROW(B86)) -> Coatings or treatments | B87: breathable, vapor-permeable coatings, including lime-based plaster and natural mineral paints | C87: — | D87: lime, clay, silicate, and occasionally bio-based mineral coatings | E87: Technical data sheet 06/2025 (Range by Kinnane et al., 2016)
A88: =+INDEX(Categories[Parameter],ROW(B87)) -> PPE requirements
A89: =+INDEX(Categories[Parameter],ROW(B88)) -> Compliance certificates | B89: Yes | C89: — | D89: Yes/No | E89: General type approval from DIBT (German Institute for Building Technology)
A90: =+INDEX(Categories[Parameter],ROW(B89)) -> Sound Absorption Coefficient | B90: 0.8 | C90: Score | D90: 0.0 - 1.0 | E90: Technical data sheet 2017
A91: =+INDEX(Categories[Parameter],ROW(B90)) -> Sound Attenuation Index | B91: >-41 | C91: db | E91: Technical data sheet 06/2025
A92: =+INDEX(Categories[Parameter],ROW(B91)) -> Color | B92: Natural Beige #D8C9A6 | C92: — | D92: Light beige; Pale grey; Soft brown | E92: Direct observation (Range depends on lime content, hemp shiv hue, and curing exposure)
A93: =+INDEX(Categories[Parameter],ROW(B92)) -> Odor | B93: Mild, earthy, lime-fresh scent | C93: — | D93: Neutral; Mild earthy; Strong organic | E93: Direct observation (Range depends on time from initial reaction)
A94: =+INDEX(Categories[Parameter],ROW(B93)) -> Texture | B94: Porous, fibrous, and dry to the touch | C94: — | D94: Smooth; Slightly rough; Coarse fibrous | E94: Direct observation (Range depends on mix and compaction)
A95: =+INDEX(Categories[Parameter],ROW(B94)) -> Temperature to touch | B95: Feels thermally neutral or slightly warm | C95: — | D95: Cold; Neutral; Warm | E95: Direct observation (Range depends on porosity and effusivity)
A96: =+INDEX(Categories[Parameter],ROW(B95)) -> Climate Suitability | B96: Varied | C96: — | D96: Climate specific - Climate adaptable | E96: Based on climatic performance studies and traditional building experience
A97: =+INDEX(Categories[Parameter],ROW(B96)) -> Agriculatural Value | B97: High | C97: — | D97: Low value crop - High value crop | E97: Based on climatic performance studies and traditional building experience
A98: =+INDEX(Categories[Parameter],ROW(B97)) -> Resourse Availability | B98: Regional | C98: — | D98: Scarce - Global | E98: Based on climatic performance studies and traditional building experience
A99: =+INDEX(Categories[Parameter],ROW(B98)) -> Material Aging | B99: 4 | C99: Score | D99: 1.0 - 5.0 | E99: Translated material properties
A100: =+INDEX(Categories[Parameter],ROW(B99)) -> Architectural Expression | B100: 4 | C100: Score | D100: 1.0 - 5.0 | E100: Translated material properties
...

Sheet Manual workflow
A1: Shared Parameter Name | B1: Group name | C1: Instance | D1: Value
A2: =INDEX(SharedParams[Name],ROW(B1)) -> DPP_AUT_Name | B2: Identity Data | C2: =IFERROR( IF( VLOOKUP( INDEX('Shared parameters'!$A$2:$A$200, MATCH($A2,'Shared parameters'!$B$2:$B$200,0) ), 'Parameter Categories'!$B$2:$G$200, 6, FALSE )="x", "No", IF( VLOOKUP( INDEX('Shared parameters'!$A$2:$A$200, MATCH($A2,'Shared parameters'!$B$2:$B$200,0) ), 'Parameter Categories'!$B$2:$G$200, 5, FALSE )="x", "Yes", "" ) ), "") -> No | D2: =IFERROR( VLOOKUP( INDEX('Shared parameters'!$A$2:$A$200, MATCH($A2,'Shared parameters'!$B$2:$B$200,0) ), 'Data Entry'!$A$2:$B$200, 2, FALSE ), "") -> Hempstone
A3: =INDEX(SharedParams[Name],ROW(B2)) -> DPP_AUT_ID | B3: Identity Data | C3: =IFERROR( IF( VLOOKUP( INDEX('Shared parameters'!$A$2:$A$200, MATCH($A3,'Shared parameters'!$B$2:$B$200,0) ), 'Parameter Categories'!$B$2:$G$200, 6, FALSE )="x", "No", IF( VLOOKUP( INDEX('Shared parameters'!$A$2:$A$200, MATCH($A3,'Shared parameters'!$B$2:$B$200,0) ), 'Parameter Categories'!$B$2:$G$200, 5, FALSE )="x", "Yes", "" ) ), "") -> No | D3: =IFERROR( VLOOKUP( INDEX('Shared parameters'!$A$2:$A$200, MATCH($A3,'Shared parameters'!$B$2:$B$200,0) ), 'Data Entry'!$A$2:$B$200, 2, FALSE ), "") -> Z-17.25-1299
A4: =INDEX(SharedParams[Name],ROW(B3)) -> DPP_AUT_Image | B4: Identity Data | C4: =IFERROR( IF( VLOOKUP( INDEX('Shared parameters'!$A$2:$A$200, MATCH($A4,'Shared parameters'!$B$2:$B$200,0) ), 'Parameter Categories'!$B$2:$G$200, 6, FALSE )="x", "No", IF( VLOOKUP( INDEX('Shared parameters'!$A$2:$A$200, MATCH($A4,'Shared parameters'!$B$2:$B$200,0) ), 'Parameter Categories'!$B$2:$G$200, 5, FALSE )="x", "Yes", "" ) ), "") -> Yes | D4: =IFERROR( VLOOKUP( INDEX('Shared parameters'!$A$2:$A$200, MATCH($A4,'Shared parameters'!$B$2:$B$200,0) ), 'Data Entry'!$A$2:$B$200, 2, FALSE ), "") -> ..\..\werner schönthaler\hanfsteine Sch├Ânthaler Kopie.png
A5: =INDEX(SharedParams[Name],ROW(B4)) -> DPP_AUT_GUID | B5: Identity Data | C5: =IFERROR( IF( VLOOKUP( INDEX('Shared parameters'!$A$2:$A$200, MATCH($A5,'Shared parameters'!$B$2:$B$200,0) ), 'Parameter Categories'!$B$2:$G$200, 6, FALSE )="x", "No", IF( VLOOKUP( INDEX('Shared parameters'!$A$2:$A$200, MATCH($A5,'Shared parameters'!$B$2:$B$200,0) ), 'Parameter Categories'!$B$2:$G$200, 5, FALSE )="x", "Yes", "" ) ), "") -> No | D5: =IFERROR( VLOOKUP( INDEX('Shared parameters'!$A$2:$A$200, MATCH($A5,'Shared parameters'!$B$2:$B$200,0) ), 'Data Entry'!$A$2:$B$200, 2, FALSE ), "") -> 0
A6: =INDEX(SharedParams[Name],ROW(B5)) -> DPP_AUT_MaterialType | B6: Materials and Finishes | C6: =IFERROR( IF( VLOOKUP( INDEX('Shared parameters'!$A$2:$A$200, MATCH($A6,'Shared parameters'!$B$2:$B$200,0) ), 'Parameter Categories'!$B$2:$G$200, 6, FALSE )="x", "No", IF( VLOOKUP( INDEX('Shared parameters'!$A$2:$A$200, MATCH($A6,'Shared parameters'!$B$2:$B$200,0) ), 'Parameter Categories'!$B$2:$G$200, 5, FALSE )="x", "Yes", "" ) ), "") -> No | D6: =IFERROR( VLOOKUP( INDEX('Shared parameters'!$A$2:$A$200, MATCH($A6,'Shared parameters'!$B$2:$B$200,0) ), 'Data Entry'!$A$2:$B$200, 2, FALSE ), "") -> Type II
A7: =INDEX(SharedParams[Name],ROW(B6)) -> DPP_AUT_Manufacturer | B7: Identity Data | C7: =IFERROR( IF( VLOOKUP( INDEX('Shared parameters'!$A$2:$A$200, MATCH($A7,'Shared parameters'!$B$2:$B$200,0) ), 'Parameter Categories'!$B$2:$G$200, 6, FALSE )="x", "No", IF( VLOOKUP( INDEX('Shared parameters'!$A$2:$A$200, MATCH($A7,'Shared parameters'!$B$2:$B$200,0) ), 'Parameter Categories'!$B$2:$G$200, 5, FALSE )="x", "Yes", "" ) ), "") -> No | D7: =IFERROR( VLOOKUP( INDEX('Shared parameters'!$A$2:$A$200, MATCH($A7,'Shared parameters'!$B$2:$B$200,0) ), 'Data Entry'!$A$2:$B$200, 2, FALSE ), "") -> Schönthaler Bausteinwerk GmbH
A8: =INDEX(SharedParams[Name],ROW(B7)) -> DPP_AUT_Manufacturer_URL | B8: Identity Data | C8: =IFERROR( IF( VLOOKUP( INDEX('Shared parameters'!$A$2:$A$200, MATCH($A8,'Shared parameters'!$B$2:$B$200,0) ), 'Parameter Categories'!$B$2:$G$200, 6, FALSE )="x", "No", IF( VLOOKUP( INDEX('Shared parameters'!$A$2:$A$200, MATCH($A8,'Shared parameters'!$B$2:$B$200,0) ), 'Parameter Categories'!$B$2:$G$200, 5, FALSE )="x", "Yes", "" ) ), "") -> No | D8: =IFERROR( VLOOKUP( INDEX('Shared parameters'!$A$2:$A$200, MATCH($A8,'Shared parameters'!$B$2:$B$200,0) ), 'Data Entry'!$A$2:$B$200, 2, FALSE ), "") -> https://www.hanfstein.eu/
A9: =INDEX(SharedParams[Name],ROW(B8)) -> DPP_AUT_Distribuitor | B9: Identity Data | C9: =IFERROR( IF( VLOOKUP( INDEX('Shared parameters'!$A$2:$A$200, MATCH($A9,'Shared parameters'!$B$2:$B$200,0) ), 'Parameter Categories'!$B$2:$G$200, 6, FALSE )="x", "No", IF( VLOOKUP( INDEX('Shared parameters'!$A$2:$A$200, MATCH($A9,'Shared parameters'!$B$2:$B$200,0) ), 'Parameter Categories'!$B$2:$G$200, 5, FALSE )="x", "Yes", "" ) ), "") -> Yes | D9: =IFERROR( VLOOKUP( INDEX('Shared parameters'!$A$2:$A$200, MATCH($A9,'Shared parameters'!$B$2:$B$200,0) ), 'Data Entry'!$A$2:$B$200, 2, FALSE ), "") -> NA
A10: =INDEX(SharedParams[Name],ROW(B9)) -> DPP_AUT_Distribuitor_URL | B10: Identity Data | C10: =IFERROR( IF( VLOOKUP( INDEX('Shared parameters'!$A$2:$A$200, MATCH($A10,'Shared parameters'!$B$2:$B$200,0) ), 'Parameter Categories'!$B$2:$G$200, 6, FALSE )="x", "No", IF( VLOOKUP( INDEX('Shared parameters'!$A$2:$A$200, MATCH($A10,'Shared parameters'!$B$2:$B$200,0) ), 'Parameter Categories'!$B$2:$G$200, 5, FALSE )="x", "Yes", "" ) ), "") -> Yes | D10: =IFERROR( VLOOKUP( INDEX('Shared parameters'!$A$2:$A$200, MATCH($A10,'Shared parameters'!$B$2:$B$200,0) ), 'Data Entry'!$A$2:$B$200, 2, FALSE ), "") -> NA
A11: =INDEX(SharedParams[Name],ROW(B10)) -> DPP_AUR_Supplier | B11: Identity Data | C11: =IFERROR( IF( VLOOKUP( INDEX('Shared parameters'!$A$2:$A$200, MATCH($A11,'Shared parameters'!$B$2:$B$200,0) ), 'Parameter Categories'!$B$2:$G$200, 6, FALSE )="x", "No", IF( VLOOKUP( INDEX('Shared parameters'!$A$2:$A$200, MATCH($A11,'Shared parameters'!$B$2:$B$200,0) ), 'Parameter Categories'!$B$2:$G$200, 5, FALSE )="x", "Yes", "" ) ), "") -> Yes | D11: =IFERROR( VLOOKUP( INDEX('Shared parameters'!$A$2:$A$200, MATCH($A11,'Shared parameters'!$B$2:$B$200,0) ), 'Data Entry'!$A$2:$B$200, 2, FALSE ), "") -> NA
A12: =INDEX(SharedParams[Name],ROW(B11)) -> DPP_AUR_Supplier_URL | B12: Identity Data | C12: =IFERROR( IF( VLOOKUP( INDEX('Shared parameters'!$A$2:$A$200, MATCH($A12,'Shared parameters'!$B$2:$B$200,0) ), 'Parameter Categories'!$B$2:$G$200, 6, FALSE )="x", "No", IF( VLOOKUP( INDEX('Shared parameters'!$A$2:$A$200, MATCH($A12,'Shared parameters'!$B$2:$B$200,0) ), 'Parameter Categories'!$B$2:$G$200, 5, FALSE )="x", "Yes", "" ) ), "") -> Yes | D12: =IFERROR( VLOOKUP( INDEX('Shared parameters'!$A$2:$A$200, MATCH($A12,'Shared parameters'!$B$2:$B$200,0) ), 'Data Entry'!$A$2:$B$200, 2, FALSE ), "") -> NA
A13: =INDEX(SharedParams[Name],ROW(B12)) -> DPP_AUT_TransRoute | B13: Identity Data | C13: =IFERROR( IF( VLOOKUP( INDEX('Shared parameters'!$A$2:$A$200, MATCH($A13,'Shared parameters'!$B$2:$B$200,0) ), 'Parameter Categories'!$B$2:$G$200, 6, FALSE )="x", "No", IF( VLOOKUP( INDEX('Shared parameters'!$A$2:$A$200, MATCH($A13,'Shared parameters'!$B$2:$B$200,0) ), 'Parameter Categories'!$B$2:$G$200, 5, FALSE )="x", "Yes", "" ) ), "") -> Yes | D13: =IFERROR( VLOOKUP( INDEX('Shared parameters'!$A$2:$A$200, MATCH($A13,'Shared parameters'!$B$2:$B$200,0) ), 'Data Entry'!$A$2:$B$200, 2, FALSE ), "") -> 0
... A117: =INDEX(SharedParams[Name],ROW(B116)) -> DPP_COD_LCC_EUR | B117: Data | C117: =IFERROR( IF( VLOOKUP( INDEX('Shared parameters'!$A$2:$A$200, MATCH($A117,'Shared parameters'!$B$2:$B$200,0) ), 'Parameter Categories'!$B$2:$G$200, 6, FALSE )="x", "No", IF( VLOOKUP( INDEX('Shared parameters'!$A$2:$A$200, MATCH($A117,'Shared parameters'!$B$2:$B$200,0) ), 'Parameter Categories'!$B$2:$G$200, 5, FALSE )="x", "Yes", "" ) ), "") -> No | D117: =IFERROR( VLOOKUP( INDEX('Shared parameters'!$A$2:$A$200, MATCH($A117,'Shared parameters'!$B$2:$B$200,0) ), 'Data Entry'!$A$2:$B$200, 2, FALSE ), "") -> 47.376343

Sheet Dynamo workflow (add params)
A1: Shared Parameter Name | B1: Group name | C1: Instance
A2: =INDEX(SharedParams[Name],ROW(B1)) -> DPP_AUT_Name | B2: =IFERROR( VLOOKUP( INDEX('Manual workflow'!$B$2:$B$200, MATCH($A2,'Manual workflow'!$A$2:$A$200,0) ), 'Built In Parameter groups'!$A$2:$C$200, 2, FALSE ), "") -> IdentityData | C2: =IFERROR( IF( VLOOKUP( INDEX('Shared parameters'!$A$2:$A$200, MATCH($A2,'Shared parameters'!$B$2:$B$200,0) ), 'Parameter Categories'!$B$2:$G$200, 6, FALSE )="x", "No", IF( VLOOKUP( INDEX('Shared parameters'!$A$2:$A$200, MATCH($A2,'Shared parameters'!$B$2:$B$200,0) ), 'Parameter Categories'!$B$2:$G$200, 5, FALSE )="x", "Yes", "" ) ), "") -> No
A3: =INDEX(SharedParams[Name],ROW(B2)) -> DPP_AUT_ID | B3: =IFERROR( VLOOKUP( INDEX('Manual workflow'!$B$2:$B$200, MATCH($A3,'Manual workflow'!$A$2:$A$200,0) ), 'Built In Parameter groups'!$A$2:$C$200, 2, FALSE ), "") -> IdentityData | C3: =IFERROR( IF( VLOOKUP( INDEX('Shared parameters'!$A$2:$A$200, MATCH($A3,'Shared parameters'!$B$2:$B$200,0) ), 'Parameter Categories'!$B$2:$G$200, 6, FALSE )="x", "No", IF( VLOOKUP( INDEX('Shared parameters'!$A$2:$A$200, MATCH($A3,'Shared parameters'!$B$2:$B$200,0) ), 'Parameter Categories'!$B$2:$G$200, 5, FALSE )="x", "Yes", "" ) ), "") -> No
A4: =INDEX(SharedParams[Name],ROW(B3)) -> DPP_AUT_Image | B4: =IFERROR( VLOOKUP( INDEX('Manual workflow'!$B$2:$B$200, MATCH($A4,'Manual workflow'!$A$2:$A$200,0) ), 'Built In Parameter groups'!$A$2:$C$200, 2, FALSE ), "") -> IdentityData | C4: =IFERROR( IF( VLOOKUP( INDEX('Shared parameters'!$A$2:$A$200, MATCH($A4,'Shared parameters'!$B$2:$B$200,0) ), 'Parameter Categories'!$B$2:$G$200, 6, FALSE )="x", "No", IF( VLOOKUP( INDEX('Shared parameters'!$A$2:$A$200, MATCH($A4,'Shared parameters'!$B$2:$B$200,0) ), 'Parameter Categories'!$B$2:$G$200, 5, FALSE )="x", "Yes", "" ) ), "") -> Yes
A5: =INDEX(SharedParams[Name],ROW(B4)) -> DPP_AUT_GUID | B5: =IFERROR( VLOOKUP( INDEX('Manual workflow'!$B$2:$B$200, MATCH($A5,'Manual workflow'!$A$2:$A$200,0) ), 'Built In Parameter groups'!$A$2:$C$200, 2, FALSE ), "") -> IdentityData | C5: =IFERROR( IF( VLOOKUP( INDEX('Shared parameters'!$A$2:$A$200, MATCH($A5,'Shared parameters'!$B$2:$B$200,0) ), 'Parameter Categories'!$B$2:$G$200, 6, FALSE )="x", "No", IF( VLOOKUP( INDEX('Shared parameters'!$A$2:$A$200, MATCH($A5,'Shared parameters'!$B$2:$B$200,0) ), 'Parameter Categories'!$B$2:$G$200, 5, FALSE )="x", "Yes", "" ) ), "") -> No
A6: =INDEX(SharedParams[Name],ROW(B5)) -> DPP_AUT_MaterialType | B6: =IFERROR( VLOOKUP( INDEX('Manual workflow'!$B$2:$B$200, MATCH($A6,'Manual workflow'!$A$2:$A$200,0) ), 'Built In Parameter groups'!$A$2:$C$200, 2, FALSE ), "") -> Materials | C6: =IFERROR( IF( VLOOKUP( INDEX('Shared parameters'!$A$2:$A$200, MATCH($A6,'Shared parameters'!$B$2:$B$200,0) ), 'Parameter Categories'!$B$2:$G$200, 6, FALSE )="x", "No", IF( VLOOKUP( INDEX('Shared parameters'!$A$2:$A$200, MATCH($A6,'Shared parameters'!$B$2:$B$200,0) ), 'Parameter Categories'!$B$2:$G$200, 5, FALSE )="x", "Yes", "" ) ), "") -> No
A7: =INDEX(SharedParams[Name],ROW(B6)) -> DPP_AUT_Manufacturer | B7: =IFERROR( VLOOKUP( INDEX('Manual workflow'!$B$2:$B$200, MATCH($A7,'Manual workflow'!$A$2:$A$200,0) ), 'Built In Parameter groups'!$A$2:$C$200, 2, FALSE ), "") -> IdentityData | C7: =IFERROR( IF( VLOOKUP( INDEX('Shared parameters'!$A$2:$A$200, MATCH($A7,'Shared parameters'!$B$2:$B$200,0) ), 'Parameter Categories'!$B$2:$G$200, 6, FALSE )="x", "No", IF( VLOOKUP( INDEX('Shared parameters'!$A$2:$A$200, MATCH($A7,'Shared parameters'!$B$2:$B$200,0) ), 'Parameter Categories'!$B$2:$G$200, 5, FALSE )="x", "Yes", "" ) ), "") -> No
A8: =INDEX(SharedParams[Name],ROW(B7)) -> DPP_AUT_Manufacturer_URL | B8: =IFERROR( VLOOKUP( INDEX('Manual workflow'!$B$2:$B$200, MATCH($A8,'Manual workflow'!$A$2:$A$200,0) ), 'Built In Parameter groups'!$A$2:$C$200, 2, FALSE ), "") -> IdentityData | C8: =IFERROR( IF( VLOOKUP( INDEX('Shared parameters'!$A$2:$A$200, MATCH($A8,'Shared parameters'!$B$2:$B$200,0) ), 'Parameter Categories'!$B$2:$G$200, 6, FALSE )="x", "No", IF( VLOOKUP( INDEX('Shared parameters'!$A$2:$A$200, MATCH($A8,'Shared parameters'!$B$2:$B$200,0) ), 'Parameter Categories'!$B$2:$G$200, 5, FALSE )="x", "Yes", "" ) ), "") -> No
A9: =INDEX(SharedParams[Name],ROW(B8)) -> DPP_AUT_Distribuitor | B9: =IFERROR( VLOOKUP( INDEX('Manual workflow'!$B$2:$B$200, MATCH($A9,'Manual workflow'!$A$2:$A$200,0) ), 'Built In Parameter groups'!$A$2:$C$200, 2, FALSE ), "") -> IdentityData | C9: =IFERROR( IF( VLOOKUP( INDEX('Shared parameters'!$A$2:$A$200, MATCH($A9,'Shared parameters'!$B$2:$B$200,0) ), 'Parameter Categories'!$B$2:$G$200, 6, FALSE )="x", "No", IF( VLOOKUP( INDEX('Shared parameters'!$A$2:$A$200, MATCH($A9,'Shared parameters'!$B$2:$B$200,0) ), 'Parameter Categories'!$B$2:$G$200, 5, FALSE )="x", "Yes", "" ) ), "") -> Yes
A10: =INDEX(SharedParams[Name],ROW(B9)) -> DPP_AUT_Distribuitor_URL | B10: =IFERROR( VLOOKUP( INDEX('Manual workflow'!$B$2:$B$200, MATCH($A10,'Manual workflow'!$A$2:$A$200,0) ), 'Built In Parameter groups'!$A$2:$C$200, 2, FALSE ), "") -> IdentityData | C10: =IFERROR( IF( VLOOKUP( INDEX('Shared parameters'!$A$2:$A$200, MATCH($A10,'Shared parameters'!$B$2:$B$200,0) ), 'Parameter Categories'!$B$2:$G$200, 6, FALSE )="x", "No", IF( VLOOKUP( INDEX('Shared parameters'!$A$2:$A$200, MATCH($A10,'Shared parameters'!$B$2:$B$200,0) ), 'Parameter Categories'!$B$2:$G$200, 5, FALSE )="x", "Yes", "" ) ), "") -> Yes
A11: =INDEX(SharedParams[Name],ROW(B10)) -> DPP_AUR_Supplier | B11: =IFERROR( VLOOKUP( INDEX('Manual workflow'!$B$2:$B$200, MATCH($A11,'Manual workflow'!$A$2:$A$200,0) ), 'Built In Parameter groups'!$A$2:$C$200, 2, FALSE ), "") -> IdentityData | C11: =IFERROR( IF( VLOOKUP( INDEX('Shared parameters'!$A$2:$A$200, MATCH($A11,'Shared parameters'!$B$2:$B$200,0) ), 'Parameter Categories'!$B$2:$G$200, 6, FALSE )="x", "No", IF( VLOOKUP( INDEX('Shared parameters'!$A$2:$A$200, MATCH($A11,'Shared parameters'!$B$2:$B$200,0) ), 'Parameter Categories'!$B$2:$G$200, 5, FALSE )="x", "Yes", "" ) ), "") -> Yes
A12: =INDEX(SharedParams[Name],ROW(B11)) -> DPP_AUR_Supplier_URL | B12: =IFERROR( VLOOKUP( INDEX('Manual workflow'!$B$2:$B$200, MATCH($A12,'Manual workflow'!$A$2:$A$200,0) ), 'Built In Parameter groups'!$A$2:$C$200, 2, FALSE ), "") -> IdentityData | C12: =IFERROR( IF( VLOOKUP( INDEX('Shared parameters'!$A$2:$A$200, MATCH($A12,'Shared parameters'!$B$2:$B$200,0) ), 'Parameter Categories'!$B$2:$G$200, 6, FALSE )="x", "No", IF( VLOOKUP( INDEX('Shared parameters'!$A$2:$A$200, MATCH($A12,'Shared parameters'!$B$2:$B$200,0) ), 'Parameter Categories'!$B$2:$G$200, 5, FALSE )="x", "Yes", "" ) ), "") -> Yes
A13: =INDEX(SharedParams[Name],ROW(B12)) -> DPP_AUT_TransRoute | B13: =IFERROR( VLOOKUP( INDEX('Manual workflow'!$B$2:$B$200, MATCH($A13,'Manual workflow'!$A$2:$A$200,0) ), 'Built In Parameter groups'!$A$2:$C$200, 2, FALSE ), "") -> IdentityData | C13: =IFERROR( IF( VLOOKUP( INDEX('Shared parameters'!$A$2:$A$200, MATCH($A13,'Shared parameters'!$B$2:$B$200,0) ), 'Parameter Categories'!$B$2:$G$200, 6, FALSE )="x", "No", IF( VLOOKUP( INDEX('Shared parameters'!$A$2:$A$200, MATCH($A13,'Shared parameters'!$B$2:$B$200,0) ), 'Parameter Categories'!$B$2:$G$200, 5, FALSE )="x", "Yes", "" ) ), "") -> Yes
... A117: =INDEX(SharedParams[Name],ROW(B116)) -> DPP_COD_LCC_EUR | B117: =IFERROR( VLOOKUP( INDEX('Manual workflow'!$B$2:$B$200, MATCH($A117,'Manual workflow'!$A$2:$A$200,0) ), 'Built In Parameter groups'!$A$2:$C$200, 2, FALSE ), "") -> Data | C117: =IFERROR( IF( VLOOKUP( INDEX('Shared parameters'!$A$2:$A$200, MATCH($A117,'Shared parameters'!$B$2:$B$200,0) ), 'Parameter Categories'!$B$2:$G$200, 6, FALSE )="x", "No", IF( VLOOKUP( INDEX('Shared parameters'!$A$2:$A$200, MATCH($A117,'Shared parameters'!$B$2:$B$200,0) ), 'Parameter Categories'!$B$2:$G$200, 5, FALSE )="x", "Yes", "" ) ), "") -> No

Sheet Dynamo workflow (set formula)
A1: Shared Parameter Name | B1: Formula
A2: =INDEX(SharedParams[Name],ROW(B1)) -> DPP_AUT_Name | B2: =IFERROR( IF( ISNUMBER( VLOOKUP( INDEX('Shared parameters'!$A$2:$A$200, MATCH($A2,'Shared parameters'!$B$2:$B$200,0) ), 'Data Entry'!$A$2:$B$200, 2, FALSE ) ), VLOOKUP( INDEX('Shared parameters'!$A$2:$A$200, MATCH($A2,'Shared parameters'!$B$2:$B$200,0) ), 'Data Entry'!$A$2:$B$200, 2, FALSE ), """" & VLOOKUP( INDEX('Shared parameters'!$A$2:$A$200, MATCH($A2,'Shared parameters'!$B$2:$B$200,0) ), 'Data Entry'!$A$2:$B$200, 2, FALSE ) & """" ), "") -> "Hempstone"
A3: =INDEX(SharedParams[Name],ROW(B2)) -> DPP_AUT_ID | B3: =IFERROR( IF( ISNUMBER( VLOOKUP( INDEX('Shared parameters'!$A$2:$A$200, MATCH($A3,'Shared parameters'!$B$2:$B$200,0) ), 'Data Entry'!$A$2:$B$200, 2, FALSE ) ), VLOOKUP( INDEX('Shared parameters'!$A$2:$A$200, MATCH($A3,'Shared parameters'!$B$2:$B$200,0) ), 'Data Entry'!$A$2:$B$200, 2, FALSE ), """" & VLOOKUP( INDEX('Shared parameters'!$A$2:$A$200, MATCH($A3,'Shared parameters'!$B$2:$B$200,0) ), 'Data Entry'!$A$2:$B$200, 2, FALSE ) & """" ), "") -> "Z-17.25-1299"
A4: =INDEX(SharedParams[Name],ROW(B3)) -> DPP_AUT_Image | B4: =IFERROR( IF( ISNUMBER( VLOOKUP( INDEX('Shared parameters'!$A$2:$A$200, MATCH($A4,'Shared parameters'!$B$2:$B$200,0) ), 'Data Entry'!$A$2:$B$200, 2, FALSE ) ), VLOOKUP( INDEX('Shared parameters'!$A$2:$A$200, MATCH($A4,'Shared parameters'!$B$2:$B$200,0) ), 'Data Entry'!$A$2:$B$200, 2, FALSE ), """" & VLOOKUP( INDEX('Shared parameters'!$A$2:$A$200, MATCH($A4,'Shared parameters'!$B$2:$B$200,0) ), 'Data Entry'!$A$2:$B$200, 2, FALSE ) & """" ), "") -> "..\..\werner schönthaler\hanfsteine Sch├Ânthaler Kopie.png"
A5: =INDEX(SharedParams[Name],ROW(B4)) -> DPP_AUT_GUID | B5: =IFERROR( IF( ISNUMBER( VLOOKUP( INDEX('Shared parameters'!$A$2:$A$200, MATCH($A5,'Shared parameters'!$B$2:$B$200,0) ), 'Data Entry'!$A$2:$B$200, 2, FALSE ) ), VLOOKUP( INDEX('Shared parameters'!$A$2:$A$200, MATCH($A5,'Shared parameters'!$B$2:$B$200,0) ), 'Data Entry'!$A$2:$B$200, 2, FALSE ), """" & VLOOKUP( INDEX('Shared parameters'!$A$2:$A$200, MATCH($A5,'Shared parameters'!$B$2:$B$200,0) ), 'Data Entry'!$A$2:$B$200, 2, FALSE ) & """" ), "") -> ""
A6: =INDEX(SharedParams[Name],ROW(B5)) -> DPP_AUT_MaterialType | B6: =IFERROR( IF( ISNUMBER( VLOOKUP( INDEX('Shared parameters'!$A$2:$A$200, MATCH($A6,'Shared parameters'!$B$2:$B$200,0) ), 'Data Entry'!$A$2:$B$200, 2, FALSE ) ), VLOOKUP( INDEX('Shared parameters'!$A$2:$A$200, MATCH($A6,'Shared parameters'!$B$2:$B$200,0) ), 'Data Entry'!$A$2:$B$200, 2, FALSE ), """" & VLOOKUP( INDEX('Shared parameters'!$A$2:$A$200, MATCH($A6,'Shared parameters'!$B$2:$B$200,0) ), 'Data Entry'!$A$2:$B$200, 2, FALSE ) & """" ), "") -> "Type II"
A7: =INDEX(SharedParams[Name],ROW(B6)) -> DPP_AUT_Manufacturer | B7: =IFERROR( IF( ISNUMBER( VLOOKUP( INDEX('Shared parameters'!$A$2:$A$200, MATCH($A7,'Shared parameters'!$B$2:$B$200,0) ), 'Data Entry'!$A$2:$B$200, 2, FALSE ) ), VLOOKUP( INDEX('Shared parameters'!$A$2:$A$200, MATCH($A7,'Shared parameters'!$B$2:$B$200,0) ), 'Data Entry'!$A$2:$B$200, 2, FALSE ), """" & VLOOKUP( INDEX('Shared parameters'!$A$2:$A$200, MATCH($A7,'Shared parameters'!$B$2:$B$200,0) ), 'Data Entry'!$A$2:$B$200, 2, FALSE ) & """" ), "") -> "Schönthaler Bausteinwerk GmbH"
A8: =INDEX(SharedParams[Name],ROW(B7)) -> DPP_AUT_Manufacturer_URL | B8: =IFERROR( IF( ISNUMBER( VLOOKUP( INDEX('Shared parameters'!$A$2:$A$200, MATCH($A8,'Shared parameters'!$B$2:$B$200,0) ), 'Data Entry'!$A$2:$B$200, 2, FALSE ) ), VLOOKUP( INDEX('Shared parameters'!$A$2:$A$200, MATCH($A8,'Shared parameters'!$B$2:$B$200,0) ), 'Data Entry'!$A$2:$B$200, 2, FALSE ), """" & VLOOKUP( INDEX('Shared parameters'!$A$2:$A$200, MATCH($A8,'Shared parameters'!$B$2:$B$200,0) ), 'Data Entry'!$A$2:$B$200, 2, FALSE ) & """" ), "") -> "https://www.hanfstein.eu/"
A9: =INDEX(SharedParams[Name],ROW(B8)) -> DPP_AUT_Distribuitor | B9: =IFERROR( IF( ISNUMBER( VLOOKUP( INDEX('Shared parameters'!$A$2:$A$200, MATCH($A9,'Shared parameters'!$B$2:$B$200,0) ), 'Data Entry'!$A$2:$B$200, 2, FALSE ) ), VLOOKUP( INDEX('Shared parameters'!$A$2:$A$200, MATCH($A9,'Shared parameters'!$B$2:$B$200,0) ), 'Data Entry'!$A$2:$B$200, 2, FALSE ), """" & VLOOKUP( INDEX('Shared parameters'!$A$2:$A$200, MATCH($A9,'Shared parameters'!$B$2:$B$200,0) ), 'Data Entry'!$A$2:$B$200, 2, FALSE ) & """" ), "") -> "NA"
A10: =INDEX(SharedParams[Name],ROW(B9)) -> DPP_AUT_Distribuitor_URL | B10: =IFERROR( IF( ISNUMBER( VLOOKUP( INDEX('Shared parameters'!$A$2:$A$200, MATCH($A10,'Shared parameters'!$B$2:$B$200,0) ), 'Data Entry'!$A$2:$B$200, 2, FALSE ) ), VLOOKUP( INDEX('Shared parameters'!$A$2:$A$200, MATCH($A10,'Shared parameters'!$B$2:$B$200,0) ), 'Data Entry'!$A$2:$B$200, 2, FALSE ), """" & VLOOKUP( INDEX('Shared parameters'!$A$2:$A$200, MATCH($A10,'Shared parameters'!$B$2:$B$200,0) ), 'Data Entry'!$A$2:$B$200, 2, FALSE ) & """" ), "") -> "NA"
A11: =INDEX(SharedParams[Name],ROW(B10)) -> DPP_AUR_Supplier | B11: =IFERROR( IF( ISNUMBER( VLOOKUP( INDEX('Shared parameters'!$A$2:$A$200, MATCH($A11,'Shared parameters'!$B$2:$B$200,0) ), 'Data Entry'!$A$2:$B$200, 2, FALSE ) ), VLOOKUP( INDEX('Shared parameters'!$A$2:$A$200, MATCH($A11,'Shared parameters'!$B$2:$B$200,0) ), 'Data Entry'!$A$2:$B$200, 2, FALSE ), """" & VLOOKUP( INDEX('Shared parameters'!$A$2:$A$200, MATCH($A11,'Shared parameters'!$B$2:$B$200,0) ), 'Data Entry'!$A$2:$B$200, 2, FALSE ) & """" ), "") -> "NA"
A12: =INDEX(SharedParams[Name],ROW(B11)) -> DPP_AUR_Supplier_URL | B12: =IFERROR( IF( ISNUMBER( VLOOKUP( INDEX('Shared parameters'!$A$2:$A$200, MATCH($A12,'Shared parameters'!$B$2:$B$200,0) ), 'Data Entry'!$A$2:$B$200, 2, FALSE ) ), VLOOKUP( INDEX('Shared parameters'!$A$2:$A$200, MATCH($A12,'Shared parameters'!$B$2:$B$200,0) ), 'Data Entry'!$A$2:$B$200, 2, FALSE ), """" & VLOOKUP( INDEX('Shared parameters'!$A$2:$A$200, MATCH($A12,'Shared parameters'!$B$2:$B$200,0) ), 'Data Entry'!$A$2:$B$200, 2, FALSE ) & """" ), "") -> "NA"
A13: =INDEX(SharedParams[Name],ROW(B12)) -> DPP_AUT_TransRoute | B13: =IFERROR( IF( ISNUMBER( VLOOKUP( INDEX('Shared parameters'!$A$2:$A$200, MATCH($A13,'Shared parameters'!$B$2:$B$200,0) ), 'Data Entry'!$A$2:$B$200, 2, FALSE ) ), VLOOKUP( INDEX('Shared parameters'!$A$2:$A$200, MATCH($A13,'Shared parameters'!$B$2:$B$200,0) ), 'Data Entry'!$A$2:$B$200, 2, FALSE ), """" & VLOOKUP( INDEX('Shared parameters'!$A$2:$A$200, MATCH($A13,'Shared parameters'!$B$2:$B$200,0) ), 'Data Entry'!$A$2:$B$200, 2, FALSE ) & """" ), "") -> ""
... A117: =INDEX(SharedParams[Name],ROW(B116)) -> DPP_COD_LCC_EUR | B117: =IFERROR( IF( ISNUMBER( VLOOKUP( INDEX('Shared parameters'!$A$2:$A$200, MATCH($A117,'Shared parameters'!$B$2:$B$200,0) ), 'Data Entry'!$A$2:$B$200, 2, FALSE ) ), VLOOKUP( INDEX('Shared parameters'!$A$2:$A$200, MATCH($A117,'Shared parameters'!$B$2:$B$200,0) ), 'Data Entry'!$A$2:$B$200, 2, FALSE ), """" & VLOOKUP( INDEX('Shared parameters'!$A$2:$A$200, MATCH($A117,'Shared parameters'!$B$2:$B$200,0) ), 'Data Entry'!$A$2:$B$200, 2, FALSE ) & """" ), "") -> 47.376343

Sheet Pyrevit workflow
A1: Shared Parameter Name | B1: BIP Name | C1: Instance | D1: Formula
A2: =INDEX(SharedParams[Name],ROW(B1)) -> DPP_AUT_Name | B2: =IFERROR( VLOOKUP( INDEX('Manual workflow'!$B$2:$B$200, MATCH($A2,'Manual workflow'!$A$2:$A$200,0) ), 'Built In Parameter groups'!$A$2:$C$200, 3, FALSE ), "") -> PG_IDENTITY_DATA | C2: =IFERROR(IF(VLOOKUP(INDEX('Shared parameters'!$A$2:$A$200,MATCH($A2,'Shared parameters'!$B$2:$B$200,0)),'Parameter Categories'!$B$2:$G$200,6,FALSE)="x","No",IF(VLOOKUP(INDEX('Shared parameters'!$A$2:$A$200,MATCH($A2,'Shared parameters'!$B$2:$B$200,0)),'Parameter Categories'!$B$2:$G$200,5,FALSE)="x","Yes","")),"") -> No | D2: =IFERROR( IF( ISNUMBER( VLOOKUP( INDEX('Shared parameters'!$A$2:$A$200, MATCH($A2,'Shared parameters'!$B$2:$B$200,0) ), 'Data Entry'!$A$2:$B$200, 2, FALSE ) ), VLOOKUP( INDEX('Shared parameters'!$A$2:$A$200, MATCH($A2,'Shared parameters'!$B$2:$B$200,0) ), 'Data Entry'!$A$2:$B$200, 2, FALSE ), """" & VLOOKUP( INDEX('Shared parameters'!$A$2:$A$200, MATCH($A2,'Shared parameters'!$B$2:$B$200,0) ), 'Data Entry'!$A$2:$B$200, 2, FALSE ) & """" ), "") -> "Hempstone"
A3: =INDEX(SharedParams[Name],ROW(B2)) -> DPP_AUT_ID | B3: =IFERROR( VLOOKUP( INDEX('Manual workflow'!$B$2:$B$200, MATCH($A3,'Manual workflow'!$A$2:$A$200,0) ), 'Built In Parameter groups'!$A$2:$C$200, 3, FALSE ), "") -> PG_IDENTITY_DATA | C3: =IFERROR( IF( VLOOKUP( INDEX('Shared parameters'!$A$2:$A$200, MATCH($A3,'Shared parameters'!$B$2:$B$200,0) ), 'Parameter Categories'!$B$2:$G$200, 6, FALSE )="x", "No", IF( VLOOKUP( INDEX('Shared parameters'!$A$2:$A$200, MATCH($A3,'Shared parameters'!$B$2:$B$200,0) ), 'Parameter Categories'!$B$2:$G$200, 5, FALSE )="x", "Yes", "" ) ), "") -> No | D3: =IFERROR( IF( ISNUMBER( VLOOKUP( INDEX('Shared parameters'!$A$2:$A$200, MATCH($A3,'Shared parameters'!$B$2:$B$200,0) ), 'Data Entry'!$A$2:$B$200, 2, FALSE ) ), VLOOKUP( INDEX('Shared parameters'!$A$2:$A$200, MATCH($A3,'Shared parameters'!$B$2:$B$200,0) ), 'Data Entry'!$A$2:$B$200, 2, FALSE ), """" & VLOOKUP( INDEX('Shared parameters'!$A$2:$A$200, MATCH($A3,'Shared parameters'!$B$2:$B$200,0) ), 'Data Entry'!$A$2:$B$200, 2, FALSE ) & """" ), "") -> "Z-17.25-1299"
A4: =INDEX(SharedParams[Name],ROW(B3)) -> DPP_AUT_Image | B4: =IFERROR( VLOOKUP( INDEX('Manual workflow'!$B$2:$B$200, MATCH($A4,'Manual workflow'!$A$2:$A$200,0) ), 'Built In Parameter groups'!$A$2:$C$200, 3, FALSE ), "") -> PG_IDENTITY_DATA | C4: =IFERROR( IF( VLOOKUP( INDEX('Shared parameters'!$A$2:$A$200, MATCH($A4,'Shared parameters'!$B$2:$B$200,0) ), 'Parameter Categories'!$B$2:$G$200, 6, FALSE )="x", "No", IF( VLOOKUP( INDEX('Shared parameters'!$A$2:$A$200, MATCH($A4,'Shared parameters'!$B$2:$B$200,0) ), 'Parameter Categories'!$B$2:$G$200, 5, FALSE )="x", "Yes", "" ) ), "") -> Yes | D4: =IFERROR( IF( ISNUMBER( VLOOKUP( INDEX('Shared parameters'!$A$2:$A$200, MATCH($A4,'Shared parameters'!$B$2:$B$200,0) ), 'Data Entry'!$A$2:$B$200, 2, FALSE ) ), VLOOKUP( INDEX('Shared parameters'!$A$2:$A$200, MATCH($A4,'Shared parameters'!$B$2:$B$200,0) ), 'Data Entry'!$A$2:$B$200, 2, FALSE ), """" & VLOOKUP( INDEX('Shared parameters'!$A$2:$A$200, MATCH($A4,'Shared parameters'!$B$2:$B$200,0) ), 'Data Entry'!$A$2:$B$200, 2, FALSE ) & """" ), "") -> "..\..\werner schönthaler\hanfsteine Sch├Ânthaler Kopie.png"
A5: =INDEX(SharedParams[Name],ROW(B4)) -> DPP_AUT_GUID | B5: =IFERROR( VLOOKUP( INDEX('Manual workflow'!$B$2:$B$200, MATCH($A5,'Manual workflow'!$A$2:$A$200,0) ), 'Built In Parameter groups'!$A$2:$C$200, 3, FALSE ), "") -> PG_IDENTITY_DATA | C5: =IFERROR( IF( VLOOKUP( INDEX('Shared parameters'!$A$2:$A$200, MATCH($A5,'Shared parameters'!$B$2:$B$200,0) ), 'Parameter Categories'!$B$2:$G$200, 6, FALSE )="x", "No", IF( VLOOKUP( INDEX('Shared parameters'!$A$2:$A$200, MATCH($A5,'Shared parameters'!$B$2:$B$200,0) ), 'Parameter Categories'!$B$2:$G$200, 5, FALSE )="x", "Yes", "" ) ), "") -> No | D5: =IFERROR( IF( ISNUMBER( VLOOKUP( INDEX('Shared parameters'!$A$2:$A$200, MATCH($A5,'Shared parameters'!$B$2:$B$200,0) ), 'Data Entry'!$A$2:$B$200, 2, FALSE ) ), VLOOKUP( INDEX('Shared parameters'!$A$2:$A$200, MATCH($A5,'Shared parameters'!$B$2:$B$200,0) ), 'Data Entry'!$A$2:$B$200, 2, FALSE ), """" & VLOOKUP( INDEX('Shared parameters'!$A$2:$A$200, MATCH($A5,'Shared parameters'!$B$2:$B$200,0) ), 'Data Entry'!$A$2:$B$200, 2, FALSE ) & """" ), "") -> ""
A6: =INDEX(SharedParams[Name],ROW(B5)) -> DPP_AUT_MaterialType | B6: =IFERROR( VLOOKUP( INDEX('Manual workflow'!$B$2:$B$200, MATCH($A6,'Manual workflow'!$A$2:$A$200,0) ), 'Built In Parameter groups'!$A$2:$C$200, 3, FALSE ), "") -> PG_MATERIALS | C6: =IFERROR( IF( VLOOKUP( INDEX('Shared parameters'!$A$2:$A$200, MATCH($A6,'Shared parameters'!$B$2:$B$200,0) ), 'Parameter Categories'!$B$2:$G$200, 6, FALSE )="x", "No", IF( VLOOKUP( INDEX('Shared parameters'!$A$2:$A$200, MATCH($A6,'Shared parameters'!$B$2:$B$200,0) ), 'Parameter Categories'!$B$2:$G$200, 5, FALSE )="x", "Yes", "" ) ), "") -> No | D6: =IFERROR( IF( ISNUMBER( VLOOKUP( INDEX('Shared parameters'!$A$2:$A$200, MATCH($A6,'Shared parameters'!$B$2:$B$200,0) ), 'Data Entry'!$A$2:$B$200, 2, FALSE ) ), VLOOKUP( INDEX('Shared parameters'!$A$2:$A$200, MATCH($A6,'Shared parameters'!$B$2:$B$200,0) ), 'Data Entry'!$A$2:$B$200, 2, FALSE ), """" & VLOOKUP( INDEX('Shared parameters'!$A$2:$A$200, MATCH($A6,'Shared parameters'!$B$2:$B$200,0) ), 'Data Entry'!$A$2:$B$200, 2, FALSE ) & """" ), "") -> "Type II"
A7: =INDEX(SharedParams[Name],ROW(B6)) -> DPP_AUT_Manufacturer | B7: =IFERROR( VLOOKUP( INDEX('Manual workflow'!$B$2:$B$200, MATCH($A7,'Manual workflow'!$A$2:$A$200,0) ), 'Built In Parameter groups'!$A$2:$C$200, 3, FALSE ), "") -> PG_IDENTITY_DATA | C7: =IFERROR( IF( VLOOKUP( INDEX('Shared parameters'!$A$2:$A$200, MATCH($A7,'Shared parameters'!$B$2:$B$200,0) ), 'Parameter Categories'!$B$2:$G$200, 6, FALSE )="x", "No", IF( VLOOKUP( INDEX('Shared parameters'!$A$2:$A$200, MATCH($A7,'Shared parameters'!$B$2:$B$200,0) ), 'Parameter Categories'!$B$2:$G$200, 5, FALSE )="x", "Yes", "" ) ), "") -> No | D7: =IFERROR( IF( ISNUMBER( VLOOKUP( INDEX('Shared parameters'!$A$2:$A$200, MATCH($A7,'Shared parameters'!$B$2:$B$200,0) ), 'Data Entry'!$A$2:$B$200, 2, FALSE ) ), VLOOKUP( INDEX('Shared parameters'!$A$2:$A$200, MATCH($A7,'Shared parameters'!$B$2:$B$200,0) ), 'Data Entry'!$A$2:$B$200, 2, FALSE ), """" & VLOOKUP( INDEX('Shared parameters'!$A$2:$A$200, MATCH($A7,'Shared parameters'!$B$2:$B$200,0) ), 'Data Entry'!$A$2:$B$200, 2, FALSE ) & """" ), "") -> "Schönthaler Bausteinwerk GmbH"
A8: =INDEX(SharedParams[Name],ROW(B7)) -> DPP_AUT_Manufacturer_URL | B8: =IFERROR( VLOOKUP( INDEX('Manual workflow'!$B$2:$B$200, MATCH($A8,'Manual workflow'!$A$2:$A$200,0) ), 'Built In Parameter groups'!$A$2:$C$200, 3, FALSE ), "") -> PG_IDENTITY_DATA | C8: =IFERROR( IF( VLOOKUP( INDEX('Shared parameters'!$A$2:$A$200, MATCH($A8,'Shared parameters'!$B$2:$B$200,0) ), 'Parameter Categories'!$B$2:$G$200, 6, FALSE )="x", "No", IF( VLOOKUP( INDEX('Shared parameters'!$A$2:$A$200, MATCH($A8,'Shared parameters'!$B$2:$B$200,0) ), 'Parameter Categories'!$B$2:$G$200, 5, FALSE )="x", "Yes", "" ) ), "") -> No | D8: =IFERROR( IF( ISNUMBER( VLOOKUP( INDEX('Shared parameters'!$A$2:$A$200, MATCH($A8,'Shared parameters'!$B$2:$B$200,0) ), 'Data Entry'!$A$2:$B$200, 2, FALSE ) ), VLOOKUP( INDEX('Shared parameters'!$A$2:$A$200, MATCH($A8,'Shared parameters'!$B$2:$B$200,0) ), 'Data Entry'!$A$2:$B$200, 2, FALSE ), """" & VLOOKUP( INDEX('Shared parameters'!$A$2:$A$200, MATCH($A8,'Shared parameters'!$B$2:$B$200,0) ), 'Data Entry'!$A$2:$B$200, 2, FALSE ) & """" ), "") -> "https://www.hanfstein.eu/"
A9: =INDEX(SharedParams[Name],ROW(B8)) -> DPP_AUT_Distribuitor | B9: =IFERROR( VLOOKUP( INDEX('Manual workflow'!$B$2:$B$200, MATCH($A9,'Manual workflow'!$A$2:$A$200,0) ), 'Built In Parameter groups'!$A$2:$C$200, 3, FALSE ), "") -> PG_IDENTITY_DATA | C9: =IFERROR( IF( VLOOKUP( INDEX('Shared parameters'!$A$2:$A$200, MATCH($A9,'Shared parameters'!$B$2:$B$200,0) ), 'Parameter Categories'!$B$2:$G$200, 6, FALSE )="x", "No", IF( VLOOKUP( INDEX('Shared parameters'!$A$2:$A$200, MATCH($A9,'Shared parameters'!$B$2:$B$200,0) ), 'Parameter Categories'!$B$2:$G$200, 5, FALSE )="x", "Yes", "" ) ), "") -> Yes | D9: =IFERROR( IF( ISNUMBER( VLOOKUP( INDEX('Shared parameters'!$A$2:$A$200, MATCH($A9,'Shared parameters'!$B$2:$B$200,0) ), 'Data Entry'!$A$2:$B$200, 2, FALSE ) ), VLOOKUP( INDEX('Shared parameters'!$A$2:$A$200, MATCH($A9,'Shared parameters'!$B$2:$B$200,0) ), 'Data Entry'!$A$2:$B$200, 2, FALSE ), """" & VLOOKUP( INDEX('Shared parameters'!$A$2:$A$200, MATCH($A9,'Shared parameters'!$B$2:$B$200,0) ), 'Data Entry'!$A$2:$B$200, 2, FALSE ) & """" ), "") -> "NA"
A10: =INDEX(SharedParams[Name],ROW(B9)) -> DPP_AUT_Distribuitor_URL | B10: =IFERROR( VLOOKUP( INDEX('Manual workflow'!$B$2:$B$200, MATCH($A10,'Manual workflow'!$A$2:$A$200,0) ), 'Built In Parameter groups'!$A$2:$C$200, 3, FALSE ), "") -> PG_IDENTITY_DATA | C10: =IFERROR( IF( VLOOKUP( INDEX('Shared parameters'!$A$2:$A$200, MATCH($A10,'Shared parameters'!$B$2:$B$200,0) ), 'Parameter Categories'!$B$2:$G$200, 6, FALSE )="x", "No", IF( VLOOKUP( INDEX('Shared parameters'!$A$2:$A$200, MATCH($A10,'Shared parameters'!$B$2:$B$200,0) ), 'Parameter Categories'!$B$2:$G$200, 5, FALSE )="x", "Yes", "" ) ), "") -> Yes | D10: =IFERROR( IF( ISNUMBER( VLOOKUP( INDEX('Shared parameters'!$A$2:$A$200, MATCH($A10,'Shared parameters'!$B$2:$B$200,0) ), 'Data Entry'!$A$2:$B$200, 2, FALSE ) ), VLOOKUP( INDEX('Shared parameters'!$A$2:$A$200, MATCH($A10,'Shared parameters'!$B$2:$B$200,0) ), 'Data Entry'!$A$2:$B$200, 2, FALSE ), """" & VLOOKUP( INDEX('Shared parameters'!$A$2:$A$200, MATCH($A10,'Shared parameters'!$B$2:$B$200,0) ), 'Data Entry'!$A$2:$B$200, 2, FALSE ) & """" ), "") -> "NA"
A11: =INDEX(SharedParams[Name],ROW(B10)) -> DPP_AUR_Supplier | B11: =IFERROR( VLOOKUP( INDEX('Manual workflow'!$B$2:$B$200, MATCH($A11,'Manual workflow'!$A$2:$A$200,0) ), 'Built In Parameter groups'!$A$2:$C$200, 3, FALSE ), "") -> PG_IDENTITY_DATA | C11: =IFERROR( IF( VLOOKUP( INDEX('Shared parameters'!$A$2:$A$200, MATCH($A11,'Shared parameters'!$B$2:$B$200,0) ), 'Parameter Categories'!$B$2:$G$200, 6, FALSE )="x", "No", IF( VLOOKUP( INDEX('Shared parameters'!$A$2:$A$200, MATCH($A11,'Shared parameters'!$B$2:$B$200,0) ), 'Parameter Categories'!$B$2:$G$200, 5, FALSE )="x", "Yes", "" ) ), "") -> Yes | D11: =IFERROR( IF( ISNUMBER( VLOOKUP( INDEX('Shared parameters'!$A$2:$A$200, MATCH($A11,'Shared parameters'!$B$2:$B$200,0) ), 'Data Entry'!$A$2:$B$200, 2, FALSE ) ), VLOOKUP( INDEX('Shared parameters'!$A$2:$A$200, MATCH($A11,'Shared parameters'!$B$2:$B$200,0) ), 'Data Entry'!$A$2:$B$200, 2, FALSE ), """" & VLOOKUP( INDEX('Shared parameters'!$A$2:$A$200, MATCH($A11,'Shared parameters'!$B$2:$B$200,0) ), 'Data Entry'!$A$2:$B$200, 2, FALSE ) & """" ), "") -> "NA"
A12: =INDEX(SharedParams[Name],ROW(B11)) -> DPP_AUR_Supplier_URL | B12: =IFERROR( VLOOKUP( INDEX('Manual workflow'!$B$2:$B$200, MATCH($A12,'Manual workflow'!$A$2:$A$200,0) ), 'Built In Parameter groups'!$A$2:$C$200, 3, FALSE ), "") -> PG_IDENTITY_DATA | C12: =IFERROR( IF( VLOOKUP( INDEX('Shared parameters'!$A$2:$A$200, MATCH($A12,'Shared parameters'!$B$2:$B$200,0) ), 'Parameter Categories'!$B$2:$G$200, 6, FALSE )="x", "No", IF( VLOOKUP( INDEX('Shared parameters'!$A$2:$A$200, MATCH($A12,'Shared parameters'!$B$2:$B$200,0) ), 'Parameter Categories'!$B$2:$G$200, 5, FALSE )="x", "Yes", "" ) ), "") -> Yes | D12: =IFERROR( IF( ISNUMBER( VLOOKUP( INDEX('Shared parameters'!$A$2:$A$200, MATCH($A12,'Shared parameters'!$B$2:$B$200,0) ), 'Data Entry'!$A$2:$B$200, 2, FALSE ) ), VLOOKUP( INDEX('Shared parameters'!$A$2:$A$200, MATCH($A12,'Shared parameters'!$B$2:$B$200,0) ), 'Data Entry'!$A$2:$B$200, 2, FALSE ), """" & VLOOKUP( INDEX('Shared parameters'!$A$2:$A$200, MATCH($A12,'Shared parameters'!$B$2:$B$200,0) ), 'Data Entry'!$A$2:$B$200, 2, FALSE ) & """" ), "") -> "NA"
A13: =INDEX(SharedParams[Name],ROW(B12)) -> DPP_AUT_TransRoute | B13: =IFERROR( VLOOKUP( INDEX('Manual workflow'!$B$2:$B$200, MATCH($A13,'Manual workflow'!$A$2:$A$200,0) ), 'Built In Parameter groups'!$A$2:$C$200, 3, FALSE ), "") -> PG_IDENTITY_DATA | C13: =IFERROR( IF( VLOOKUP( INDEX('Shared parameters'!$A$2:$A$200, MATCH($A13,'Shared parameters'!$B$2:$B$200,0) ), 'Parameter Categories'!$B$2:$G$200, 6, FALSE )="x", "No", IF( VLOOKUP( INDEX('Shared parameters'!$A$2:$A$200, MATCH($A13,'Shared parameters'!$B$2:$B$200,0) ), 'Parameter Categories'!$B$2:$G$200, 5, FALSE )="x", "Yes", "" ) ), "") -> Yes | D13: =IFERROR( IF( ISNUMBER( VLOOKUP( INDEX('Shared parameters'!$A$2:$A$200, MATCH($A13,'Shared parameters'!$B$2:$B$200,0) ), 'Data Entry'!$A$2:$B$200, 2, FALSE ) ), VLOOKUP( INDEX('Shared parameters'!$A$2:$A$200, MATCH($A13,'Shared parameters'!$B$2:$B$200,0) ), 'Data Entry'!$A$2:$B$200, 2, FALSE ), """" & VLOOKUP( INDEX('Shared parameters'!$A$2:$A$200, MATCH($A13,'Shared parameters'!$B$2:$B$200,0) ), 'Data Entry'!$A$2:$B$200, 2, FALSE ) & """" ), "") -> ""
A14: =INDEX(SharedParams[Name],ROW(B13)) -> DPP_AUT_Traceability | B14: =IFERROR( VLOOKUP( INDEX('Manual workflow'!$B$2:$B$200, MATCH($A14,'Manual workflow'!$A$2:$A$200,0) ), 'Built In Parameter groups'!$A$2:$C$200, 3, FALSE ), "") -> PG_IDENTITY_DATA | C14: =IFERROR( IF( VLOOKUP( INDEX('Shared parameters'!$A$2:$A$200, MATCH($A14,'Shared parameters'!$B$2:$B$200,0) ), 'Parameter Categories'!$B$2:$G$200, 6, FALSE )="x", "No", IF( VLOOKUP( INDEX('Shared parameters'!$A$2:$A$200, MATCH($A14,'Shared parameters'!$B$2:$B$200,0) ), 'Parameter Categories'!$B$2:$G$200, 5, FALSE )="x", "Yes", "" ) ), "") -> No | D14: =IFERROR( IF( ISNUMBER( VLOOKUP( INDEX('Shared parameters'!$A$2:$A$200, MATCH($A14,'Shared parameters'!$B$2:$B$200,0) ), 'Data Entry'!$A$2:$B$200, 2, FALSE ) ), VLOOKUP( INDEX('Shared parameters'!$A$2:$A$200, MATCH($A14,'Shared parameters'!$B$2:$B$200,0) ), 'Data Entry'!$A$2:$B$200, 2, FALSE ), """" & VLOOKUP( INDEX('Shared parameters'!$A$2:$A$200, MATCH($A14,'Shared parameters'!$B$2:$B$200,0) ), 'Data Entry'!$A$2:$B$200, 2, FALSE ) & """" ), "") -> "a1b2c3d4-e5f6-7890-1234-567890abcdef"
... A117: =INDEX(SharedParams[Name],ROW(B116)) -> DPP_COD_LCC_EUR | B117: =IFERROR( VLOOKUP( INDEX('Manual workflow'!$B$2:$B$200, MATCH($A117,'Manual workflow'!$A$2:$A$200,0) ), 'Built In Parameter groups'!$A$2:$C$200, 3, FALSE ), "") -> PG_DATA | C117: =IFERROR( IF( VLOOKUP( INDEX('Shared parameters'!$A$2:$A$200, MATCH($A117,'Shared parameters'!$B$2:$B$200,0) ), 'Parameter Categories'!$B$2:$G$200, 6, FALSE )="x", "No", IF( VLOOKUP( INDEX('Shared parameters'!$A$2:$A$200, MATCH($A117,'Shared parameters'!$B$2:$B$200,0) ), 'Parameter Categories'!$B$2:$G$200, 5, FALSE )="x", "Yes", "" ) ), "") -> No | D117: =IFERROR( IF( ISNUMBER( VLOOKUP( INDEX('Shared parameters'!$A$2:$A$200, MATCH($A117,'Shared parameters'!$B$2:$B$200,0) ), 'Data Entry'!$A$2:$B$200, 2, FALSE ) ), VLOOKUP( INDEX('Shared parameters'!$A$2:$A$200, MATCH($A117,'Shared parameters'!$B$2:$B$200,0) ), 'Data Entry'!$A$2:$B$200, 2, FALSE ), """" & VLOOKUP( INDEX('Shared parameters'!$A$2:$A$200, MATCH($A117,'Shared parameters'!$B$2:$B$200,0) ), 'Data Entry'!$A$2:$B$200, 2, FALSE ) & """" ), "") -> 47.376343

Sheet Parameter mapping
A1: Shared Parameter Name | B1: Revit Built-In Parameter | C1: IFC Standard Pset | D1: Custom Pset (DPP) | E1: Property Type | F1: Ontology property | G1: URI
A2: =INDEX(SharedParams[Name],ROW(B1)) -> DPP_AUT_Name | B2: Name | C2: IfcRoot | E2: String | F2: PROPS:hasGlobalIdIfcRoot
A3: =INDEX(SharedParams[Name],ROW(B2)) -> DPP_AUT_ID | B3: Model | C3: IfcRoot | E3: Identifier | F3: SCHEMA:label/name
A4: =INDEX(SharedParams[Name],ROW(B3)) -> DPP_AUT_Image | B4: Type Image | C4: IfcDocumentReference | F4: SCHEMA:image
A5: =INDEX(SharedParams[Name],ROW(B4)) -> DPP_AUT_GUID | B5: Element GUID | C5: IfcRoot | E5: Identifier | F5: PROPS:hasGUID
A6: =INDEX(SharedParams[Name],ROW(B5)) -> DPP_AUT_MaterialType | B6: MATERIAL_ID_PARAM | C6: IfcMaterial | E6: String | F6: SCHEMA:model
A7: =INDEX(SharedParams[Name],ROW(B6)) -> DPP_AUT_Manufacturer | B7: Manufacturer | C7: Pset_ManufacturerTypeInformation | E7: String | F7: BPM:manufaturer
A8: =INDEX(SharedParams[Name],ROW(B7)) -> DPP_AUT_Manufacturer_URL | B8: ALL_MODEL_URL | C8: Pset_ManufacturerTypeInformation | E8: String | F8: SCHEMA:url
A9: =INDEX(SharedParams[Name],ROW(B8)) -> DPP_AUT_Distribuitor | C9: Custom Pset | D9: Pset_DDPHempcrete | E9: String | F9: SCHEMA:distribuitor
A10: =INDEX(SharedParams[Name],ROW(B9)) -> DPP_AUT_Distribuitor_URL | C10: Custom Pset | D10: Pset_DDPHempcrete | E10: String | F10: SCHEMA:url
A11: =INDEX(SharedParams[Name],ROW(B10)) -> DPP_AUR_Supplier | C11: Custom Pset | D11: Pset_DDPHempcrete | E11: String | F11: SCHEMA:supplier
A12: =INDEX(SharedParams[Name],ROW(B11)) -> DPP_AUR_Supplier_URL | C12: Custom Pset | D12: Pset_DDPHempcrete | E12: String | F12: SCHEMA:url
A13: =INDEX(SharedParams[Name],ROW(B12)) -> DPP_AUT_TransRoute | C13: Custom Pset | D13: Pset_DDPHempcrete | E13: String | F13: PROV:wasderivedfrom
A14: =INDEX(SharedParams[Name],ROW(B13)) -> DPP_AUT_Traceability | C14: Custom Pset | D14: Pset_DDPHempcrete | E14: Identifier | F14: PROV:wasAttributedTo
A15: =INDEX(SharedParams[Name],ROW(B14)) -> DPP_AUT_Origin | C15: Pset_ManufacturerTypeInformation | E15: String | F15: PROV:wasGeneratedby/location
A16: =INDEX(SharedParams[Name],ROW(B15)) -> DPP_AUT_Version | B16: Type Mark | C16: Pset_ManufacturerTypeInformation | E16: String
A17: =INDEX(SharedParams[Name],ROW(B16)) -> DPP_MAT_Material | B17: Material.Name | C17: IfcMaterial | E17: String | F17: SCHEMA:material
A18: =INDEX(SharedParams[Name],ROW(B17)) -> DPP_MAT_Components | C18: Custom Pset | D18: Pset_DDPHempcrete | E18: String | F18: BPM:hasMaterial
A19: =INDEX(SharedParams[Name],ROW(B18)) -> DPP_MAT_Composition | B19: ALL_MODEL_DESCRIPTION | C19: IfcMaterial | E19: String | F19: BPM:materialcomposition
A20: =INDEX(SharedParams[Name],ROW(B19)) -> DPP_AUT_TypeDimension | B20: TYPE_NAME | C20: IfcRoot | E20: String | F20: SCHEMA:additionaltype
A21: =INDEX(SharedParams[Name],ROW(B20)) -> DPP_DIM_Height_mm | B21: Height | C21: IfcElementQuantity | E21: Length | F21: QUDT:height/value
A22: =INDEX(SharedParams[Name],ROW(B21)) -> DPP_DIM_Length_mm | B22: Length | C22: IfcElementQuantity | E22: Length | F22: QUDT:lenght/value
A23: =INDEX(SharedParams[Name],ROW(B22)) -> DPP_DIM_Width_mm | B23: Width | C23: IfcElementQuantity | E23: Length | F23: QUDT:width/value
A24: =INDEX(SharedParams[Name],ROW(B23)) -> DPP_DIM_Volume_m3 | B24: Volume | C24: IfcElementQuantity | E24: Volume | F24: QUDT:volume/value
A25: =INDEX(SharedParams[Name],ROW(B24)) -> DPP_DAT_DryDensity_kgm3 | B25: Dry Density | C25: Pset_MaterialCommon | E25: Real | F25: QUDT:density/value
A26: =INDEX(SharedParams[Name],ROW(B25)) -> DPP_DAT_EqDensity_kgm3 | B26: Equilibrium Density | C26: Pset_MaterialCommon | E26: Real | F26: QUDT:density/value
A27: =INDEX(SharedParams[Name],ROW(B26)) -> DPP_DAT_Weight_kg | B27: Weight | C27: Pset_MaterialCommon | E27: Mass | F27: QUDT:weight/value
A28: =INDEX(SharedParams[Name],ROW(B27)) -> DPP_DAT_CompressiveStrenght_Mpa | B28: Compressive Strenght | C28: Pset_MaterialCommon | E28: Real | F28: PROPS:compressivestrength
A29: =INDEX(SharedParams[Name],ROW(B28)) -> DPP_DAT_ShearStrenght_Mpa | B29: PHY_MATERIAL_PARAM_STRUCTURAL | C29: Pset_MaterialCommon | E29: Real | F29: PROPS:tensilestrength
A30: =INDEX(SharedParams[Name],ROW(B29)) -> DPP_DAT_ThermalConductivity_WmK | B30: Thermal Conductivity | C30: Pset_MaterialCommon | E30: Real | F30: PROPS:thermalconductivity
A31: =INDEX(SharedParams[Name],ROW(B30)) -> DPP_DAT_Uvalue_Wm2K | B31: THERMAL_MATERIAL_PARAM | C31: Pset_MaterialCommon | E31: Real
A32: =INDEX(SharedParams[Name],ROW(B31)) -> DPP_DAT_SpeHeatCap_JkgK | B32: THERMAL_MATERIAL_PARAM | C32: Pset_MaterialCommon | E32: Real | F32: PROPS:tensilestrength
A33: =INDEX(SharedParams[Name],ROW(B32)) -> DPP_DAT_PhaseShift_Hours | C33: Pset_MaterialCommon | E33: Real | F33: PROPS:phasePermeability
A34: =INDEX(SharedParams[Name],ROW(B33)) -> DPP_DAT_MoistureBuffer_m2%HR | C34: Custom Pset | D34: Pset_DDPHempcrete | E34: Real | F34: DPP:moistureBuffer
A35: =INDEX(SharedParams[Name],ROW(B34)) -> DPP_DAT_VaporDiffμ_wet | C35: Pset_MaterialHygroscopic | E35: Real | F35: PROPS:vaporPermeability
A36: =INDEX(SharedParams[Name],ROW(B35)) -> DPP_DAT_VaporDiffμ_dry | C36: Pset_MaterialHygroscopic | E36: Real | F36: PROPS:vaporPermeability
A37: =INDEX(SharedParams[Name],ROW(B36)) -> DPP_DAT_VaporAbsorption | C37: Pset_MaterialHygroscopic | E37: Real | F37: PROPS:porosity
A38: =INDEX(SharedParams[Name],ROW(B37)) -> DPP_DAT_StandarCompliance | B38: ALL_MODEL_TYPE_COMMENTS | C38: IfcDocumentReference | E38: Boolean | F38: SCHEMA:comformsTo
A39: =INDEX(SharedParams[Name],ROW(B38)) -> DPP_CIR_ConnectionType | C39: Custom Pset | D39: Pset_DDPHempcrete | E39: String
A40: =INDEX(SharedParams[Name],ROW(B39)) -> DPP_CIR_ConnectionScore | C40: Custom Pset | D40: Pset_DDPHempcrete | E40: Real
A41: =INDEX(SharedParams[Name],ROW(B40)) -> DPP_CIR_Prefabrication | C41: Custom Pset | D41: Pset_DDPHempcrete | E41: Boolean | F41: DPP:prefabrication
A42: =INDEX(SharedParams[Name],ROW(B41)) -> DPP_CIR_PrefabricationFactor | C42: Custom Pset | D42: Pset_DDPHempcrete | E42: Real | F42: DPP:prefabrication
A43: =INDEX(SharedParams[Name],ROW(B42)) -> DPP_CIR_DeconstructabilityScore | C43: Custom Pset | D43: Pset_DDPHempcrete | E43: Real | F43: DPP:deconstructability
A44: =INDEX(SharedParams[Name],ROW(B43)) -> DPP_CIR_RecyclingPotential | C44: Custom Pset | D44: Pset_DDPHempcrete | E44: Real | F44: DPP:recyclingPotential
A45: =INDEX(SharedParams[Name],ROW(B44)) -> DPP_CIR_Reusability | C45: Custom Pset | D45: Pset_DDPHempcrete | E45: Boolean | F45: DPP:Reusability
A46: =INDEX(SharedParams[Name],ROW(B45)) -> DPP_CIR_ReusabilityPotential | C46: Custom Pset | D46: Pset_DDPHempcrete | E46: Real | F46: DPP:reusabilityPotential
A47: =INDEX(SharedParams[Name],ROW(B46)) -> DPP_CIR_RecoveryScore | C47: Custom Pset | D47: Pset_DDPHempcrete | E47: Real | F47: DPP:recoveryScore
A48: =INDEX(SharedParams[Name],ROW(B47)) -> DPP_CIR_Disassemblypotential | C48: Custom Pset | D48: Pset_DDPHempcrete | E48: Real | F48: DPP:dissasemblypotential
A49: =INDEX(SharedParams[Name],ROW(B48)) -> DPP_CIR_DisassemblyInstructions | C49: Custom Pset | D49: Pset_DDPHempcrete | E49: String | F49: DPP:dissasemblyinstructions
A50: =INDEX(SharedParams[Name],ROW(B49)) -> DPP_CIR_SecondaryUse | C50: Custom Pset | D50: Pset_DDPHempcrete | E50: String
A51: =INDEX(SharedParams[Name],ROW(B50)) -> DPP_CIR_EndofLifeRecomendations | C51: IfcDocumentReference | E51: String
A52: =INDEX(SharedParams[Name],ROW(B51)) -> DPP_END_EPD | C52: IfcDocumentReference | E52: Boolean | F52: DPP:environmentalproductdeclaration
A53: =INDEX(SharedParams[Name],ROW(B52)) -> DPP_END_EPD_URL | C53: IfcDocumentReference | E53: String | F53: SCHEMA:url
A54: =INDEX(SharedParams[Name],ROW(B53)) -> DPP_END_GWP_kgCO₂eq | C54: Pset_EnvironmentalImpactIndicators | E54: Real | F54: DPP:globalWarmingPotential
A55: =INDEX(SharedParams[Name],ROW(B54)) -> DPP_END_PEI_MJKg | C55: Pset_EnvironmentalImpactIndicators | E55: Real | F55: DPP:primaryEnergyIndicator
A56: =INDEX(SharedParams[Name],ROW(B55)) -> DPP_END_PERT_MJKg | C56: Pset_EnvironmentalImpactIndicators | E56: Real | F56: DPP:renewablePrimaryEnergy
A57: =INDEX(SharedParams[Name],ROW(B56)) -> DPP_END_PENRT_MJKg | C57: Pset_EnvironmentalImpactIndicators | E57: Real | F57: DPP:nonRenewablePrimaryEnergy
A58: =INDEX(SharedParams[Name],ROW(B57)) -> DPP_END_AP_kgSO₂eq | C58: Pset_EnvironmentalImpactIndicators | E58: Real
A59: =INDEX(SharedParams[Name],ROW(B58)) -> DPP_END_EmbodiedCarbon_kgCO₂eq | C59: Pset_EnvironmentalImpactIndicators | E59: Real | F59: DPP:embodiedcarbon
A60: =INDEX(SharedParams[Name],ROW(B59)) -> DPP_END_BiogenicCarbon_kgCO₂eq | C60: Pset_EnvironmentalImpactIndicators | E60: Real | F60: DPP:biogeniccarbon
A61: =INDEX(SharedParams[Name],ROW(B60)) -> DPP_END_EndoflifeEmissions_kgCO₂eq | C61: Pset_EnvironmentalImpactIndicators | E61: Real | F61: DPP:embodiedemissions
A62: =INDEX(SharedParams[Name],ROW(B61)) -> DPP_CIR_CircularityIndex | C62: Custom Pset | D62: Pset_DDPHempcrete | E62: Real | F62: DPP:circularityIndex
A63: =INDEX(SharedParams[Name],ROW(B62)) -> DPP_END_Ei | C63: Custom Pset | D63: Pset_DDPHempcrete | E63: Real
A64: =INDEX(SharedParams[Name],ROW(B63)) -> DPP_END_w | C64: Custom Pset | D64: Pset_DDPHempcrete | E64: Real
A65: =INDEX(SharedParams[Name],ROW(B64)) -> DPP_END_EnvironmentalScore | C65: Custom Pset | D65: Pset_DDPHempcrete | E65: Real | F65: DPP:environmentalscore
A66: =INDEX(SharedParams[Name],ROW(B65)) -> DPP_TMP_ServiceLife_years | C66: Pset_Maintenance | E66: Real | F66: DPP:servicelife
A67: =INDEX(SharedParams[Name],ROW(B66)) -> DPP_TMP_Manteinance | C67: Pset_Maintenance | E67: Real | F67: DPP:manteinanceInterval
A68: =INDEX(SharedParams[Name],ROW(B67)) -> DPP_TMP_Soursing_km | C68: Custom Pset | D68: Pset_DDPHempcrete | E68: Time | F68: DPP:sourcingDistance
A69: =INDEX(SharedParams[Name],ROW(B68)) -> DPP_TMP_Warranty | C69: Pset_Maintenance | E69: String | F69: SCHEMA:warranty
A70: =INDEX(SharedParams[Name],ROW(B69)) -> DPP_TMP_Warranty_months | C70: Pset_Maintenance | E70: Boolean
A71: =INDEX(SharedParams[Name],ROW(B70)) -> DPP_TMP_UpdateHistory | C71: IfcDocumentReference | E71: Time
A72: =INDEX(SharedParams[Name],ROW(B71)) -> DPP_SAD_HPD | C72: IfcDocumentReference | E72: String | F72: DPP:healthproductdeclaration
A73: =INDEX(SharedParams[Name],ROW(B72)) -> DPP_SAD_HPD_URL | C73: IfcDocumentReference | E73: Boolean | F73: SCHEMA:url
A74: =INDEX(SharedParams[Name],ROW(B73)) -> DPP_SAD_HazardClassification | C74: Pset_HealthAndSafety | E74: String | F74: DPP:hazardclasification
A75: =INDEX(SharedParams[Name],ROW(B74)) -> DPP_SAD_PM_CTUh | C75: Custom Pset | D75: Pset_DDPHempcrete | E75: String | F75: DPP:vocToxicity
A76: =INDEX(SharedParams[Name],ROW(B75)) -> DPP_SAD_IRP_kBqU235eq | C76: Custom Pset | D76: Pset_DDPHempcrete | E76: Real
A77: =INDEX(SharedParams[Name],ROW(B76)) -> DPP_SAD_ETPfw_CTUe | C77: Custom Pset | D77: Pset_DDPHempcrete | E77: Real
A78: =INDEX(SharedParams[Name],ROW(B77)) -> DPP_SAD_HRPc_CTUh | C78: Custom Pset | D78: Pset_DDPHempcrete | E78: Real
A79: =INDEX(SharedParams[Name],ROW(B78)) -> DPP_SAD_HRPnc_CTUh | C79: Custom Pset | D79: Pset_DDPHempcrete | E79: Real
A80: =INDEX(SharedParams[Name],ROW(B79)) -> DPP_SAD_SQP | C80: Custom Pset | D80: Pset_DDPHempcrete | E80: Real
A81: =INDEX(SharedParams[Name],ROW(B80)) -> DPP_SAD_Toxicity | C81: Custom Pset | D81: Pset_DDPHempcrete | E81: Boolean | F81: DPP:Toxicity
A82: =INDEX(SharedParams[Name],ROW(B81)) -> DPP_SAD_Fire_Class | B82: FIRE_RATING | C82: Pset_FireRating | E82: String
A83: =INDEX(SharedParams[Name],ROW(B82)) -> DPP_SAD_Fire_Ssubclass | B83: FIRE_RATING | C83: Pset_FireRating | E83: String | F83: DPP:smokeResistance
A84: =INDEX(SharedParams[Name],ROW(B83)) -> DPP_SAD_Fire_Dsubclass | B84: FIRE_RATING | C84: Pset_FireRating | E84: String | F84: DPP:FireParticles
A85: =INDEX(SharedParams[Name],ROW(B84)) -> DPP_SAD_FireResistance | B85: FIRE_RATING | C85: Pset_FireRating | E85: String | F85: PROPS:firerating
A86: =INDEX(SharedParams[Name],ROW(B85)) -> DPP_SAD_Coatings | C86: Pset_Coating | E86: Boolean
A87: =INDEX(SharedParams[Name],ROW(B86)) -> DPP_SAD_CoatingType | C87: Pset_Coating | E87: String | F87: BPO:surfaceFinish
A88: =INDEX(SharedParams[Name],ROW(B87)) -> DPP_SAD_PPERequirements | C88: Pset_HealthAndSafety | E88: String
A89: =INDEX(SharedParams[Name],ROW(B88)) -> DPP_SAD_Compliance | C89: IfcDocumentReference | E89: Boolean | F89: SCHEMA:comformsTo
A90: =INDEX(SharedParams[Name],ROW(B89)) -> DPP_ASD_SAC | B90: ACOUSTICS_SOUND_COEFFICIENT | C90: Pset_AcousticMaterial | E90: Real | F90: PROPS:acousticRating
A91: =INDEX(SharedParams[Name],ROW(B90)) -> DPP_ASD_SAI_db | C91: Pset_AcousticMaterial | E91: Real | F91: DPP:soundLevel
A92: =INDEX(SharedParams[Name],ROW(B91)) -> DPP_ASD_Color | C92: Pset_SurfaceProperties | E92: String | F92: SCHEMA:color
A93: =INDEX(SharedParams[Name],ROW(B92)) -> DPP_ASD_Odor | C93: Pset_SurfaceProperties | E93: String | F93: SCHEMA:odor
A94: =INDEX(SharedParams[Name],ROW(B93)) -> DPP_ASD_Texture | C94: Pset_SurfaceProperties | E94: String | F94: SCHEMA:texture
A95: =INDEX(SharedParams[Name],ROW(B94)) -> DPP_ASD_Temp | C95: Pset_SurfaceProperties | E95: String | F95: QUDT:temperature
A96: =INDEX(SharedParams[Name],ROW(B95)) -> DPP_ASD_ClimateSuitability | C96: Custom Pset | D96: Pset_DDPHempcrete | E96: String
A97: =INDEX(SharedParams[Name],ROW(B96)) -> DPP_ASD_AgriculturalValue | C97: Custom Pset | D97: Pset_DDPHempcrete | E97: String
A98: =INDEX(SharedParams[Name],ROW(B97)) -> DPP_ASD_ResourseAvailability | C98: Custom Pset | D98: Pset_DDPHempcrete | E98: String
A99: =INDEX(SharedParams[Name],ROW(B98)) -> DPP_ASD_Aging | C99: Custom Pset | D99: Pset_DDPHempcrete | E99: Integer
A100: =INDEX(SharedParams[Name],ROW(B99)) -> DPP_ASD_Architectural | C100: Custom Pset | D100: Pset_DDPHempcrete | E100: Integer
...

Sheet Final Dataset
A1: Parameter | B1: Data | C1: Unit | D1: Range
A2: =INDEX(SharedParams[Name],ROW(B1)) -> DPP_AUT_Name | B2: =IFERROR( VLOOKUP( INDEX('Shared parameters'!$A$2:$A$200, MATCH($A2,'Shared parameters'!$B$2:$B$200,0) ), 'Data Entry'!$A$2:$B$200, 2, FALSE ), "") -> Hempstone | C2: =IFERROR( VLOOKUP( INDEX('Shared parameters'!$A$2:$A$200, MATCH($A2,'Shared parameters'!$B$2:$B$200,0) ), 'Data Entry'!$A$2:$C$200, 3, FALSE ), "") -> — | D2: =IFERROR( VLOOKUP( INDEX('Shared parameters'!$A$2:$A$200, MATCH($A2,'Shared parameters'!$B$2:$B$200,0) ), 'Data Entry'!$A$2:$D$200, 4, FALSE ), "") -> —
A3: =INDEX(SharedParams[Name],ROW(B2)) -> DPP_AUT_ID | B3: =IFERROR( VLOOKUP( INDEX('Shared parameters'!$A$2:$A$200, MATCH($A3,'Shared parameters'!$B$2:$B$200,0) ), 'Data Entry'!$A$2:$B$200, 2, FALSE ), "") -> Z-17.25-1299 | C3: =IFERROR( VLOOKUP( INDEX('Shared parameters'!$A$2:$A$200, MATCH($A3,'Shared parameters'!$B$2:$B$200,0) ), 'Data Entry'!$A$2:$C$200, 3, FALSE ), "") -> ID | D3: =IFERROR( VLOOKUP( INDEX('Shared parameters'!$A$2:$A$200, MATCH($A3,'Shared parameters'!$B$2:$B$200,0) ), 'Data Entry'!$A$2:$D$200, 4, FALSE ), "") -> —
A4: =INDEX(SharedParams[Name],ROW(B3)) -> DPP_AUT_Image | B4: =IFERROR( VLOOKUP( INDEX('Shared parameters'!$A$2:$A$200, MATCH($A4,'Shared parameters'!$B$2:$B$200,0) ), 'Data Entry'!$A$2:$B$200, 2, FALSE ), "") -> ..\..\werner schönthaler\hanfsteine Sch├Ânthaler Kopie.png | C4: =IFERROR( VLOOKUP( INDEX('Shared parameters'!$A$2:$A$200, MATCH($A4,'Shared parameters'!$B$2:$B$200,0) ), 'Data Entry'!$A$2:$C$200, 3, FALSE ), "") -> — | D4: =IFERROR( VLOOKUP( INDEX('Shared parameters'!$A$2:$A$200, MATCH($A4,'Shared parameters'!$B$2:$B$200,0) ), 'Data Entry'!$A$2:$D$200, 4, FALSE ), "") -> —
A5: =INDEX(SharedParams[Name],ROW(B4)) -> DPP_AUT_GUID | B5: =IFERROR( VLOOKUP( INDEX('Shared parameters'!$A$2:$A$200, MATCH($A5,'Shared parameters'!$B$2:$B$200,0) ), 'Data Entry'!$A$2:$B$200, 2, FALSE ), "") -> 0 | C5: =IFERROR( VLOOKUP( INDEX('Shared parameters'!$A$2:$A$200, MATCH($A5,'Shared parameters'!$B$2:$B$200,0) ), 'Data Entry'!$A$2:$C$200, 3, FALSE ), "") -> GUID | D5: =IFERROR( VLOOKUP( INDEX('Shared parameters'!$A$2:$A$200, MATCH($A5,'Shared parameters'!$B$2:$B$200,0) ), 'Data Entry'!$A$2:$D$200, 4, FALSE ), "") -> —
A6: =INDEX(SharedParams[Name],ROW(B5)) -> DPP_AUT_MaterialType | B6: =IFERROR( VLOOKUP( INDEX('Shared parameters'!$A$2:$A$200, MATCH($A6,'Shared parameters'!$B$2:$B$200,0) ), 'Data Entry'!$A$2:$B$200, 2, FALSE ), "") -> Type II | C6: =IFERROR( VLOOKUP( INDEX('Shared parameters'!$A$2:$A$200, MATCH($A6,'Shared parameters'!$B$2:$B$200,0) ), 'Data Entry'!$A$2:$C$200, 3, FALSE ), "") -> — | D6: =IFERROR( VLOOKUP( INDEX('Shared parameters'!$A$2:$A$200, MATCH($A6,'Shared parameters'!$B$2:$B$200,0) ), 'Data Entry'!$A$2:$D$200, 4, FALSE ), "") -> Type I (Ingredients); Type II (Modular); Type III (Sub-Components)
A7: =INDEX(SharedParams[Name],ROW(B6)) -> DPP_AUT_Manufacturer | B7: =IFERROR( VLOOKUP( INDEX('Shared parameters'!$A$2:$A$200, MATCH($A7,'Shared parameters'!$B$2:$B$200,0) ), 'Data Entry'!$A$2:$B$200, 2, FALSE ), "") -> Schönthaler Bausteinwerk GmbH | C7: =IFERROR( VLOOKUP( INDEX('Shared parameters'!$A$2:$A$200, MATCH($A7,'Shared parameters'!$B$2:$B$200,0) ), 'Data Entry'!$A$2:$C$200, 3, FALSE ), "") -> — | D7: =IFERROR( VLOOKUP( INDEX('Shared parameters'!$A$2:$A$200, MATCH($A7,'Shared parameters'!$B$2:$B$200,0) ), 'Data Entry'!$A$2:$D$200, 4, FALSE ), "") -> —
A8: =INDEX(SharedParams[Name],ROW(B7)) -> DPP_AUT_Manufacturer_URL | B8: =IFERROR( VLOOKUP( INDEX('Shared parameters'!$A$2:$A$200, MATCH($A8,'Shared parameters'!$B$2:$B$200,0) ), 'Data Entry'!$A$2:$B$200, 2, FALSE ), "") -> https://www.hanfstein.eu/ | C8: =IFERROR( VLOOKUP( INDEX('Shared parameters'!$A$2:$A$200, MATCH($A8,'Shared parameters'!$B$2:$B$200,0) ), 'Data Entry'!$A$2:$C$200, 3, FALSE ), "") -> — | D8: =IFERROR( VLOOKUP( INDEX('Shared parameters'!$A$2:$A$200, MATCH($A8,'Shared parameters'!$B$2:$B$200,0) ), 'Data Entry'!$A$2:$D$200, 4, FALSE ), "") -> —
A9: =INDEX(SharedParams[Name],ROW(B8)) -> DPP_AUT_Distribuitor | B9: =IFERROR( VLOOKUP( INDEX('Shared parameters'!$A$2:$A$200, MATCH($A9,'Shared parameters'!$B$2:$B$200,0) ), 'Data Entry'!$A$2:$B$200, 2, FALSE ), "") -> NA | C9: =IFERROR( VLOOKUP( INDEX('Shared parameters'!$A$2:$A$200, MATCH($A9,'Shared parameters'!$B$2:$B$200,0) ), 'Data Entry'!$A$2:$C$200, 3, FALSE ), "") -> — | D9: =IFERROR( VLOOKUP( INDEX('Shared parameters'!$A$2:$A$200, MATCH($A9,'Shared parameters'!$B$2:$B$200,0) ), 'Data Entry'!$A$2:$D$200, 4, FALSE ), "") -> NA
A10: =INDEX(SharedParams[Name],ROW(B9)) -> DPP_AUT_Distribuitor_URL | B10: =IFERROR( VLOOKUP( INDEX('Shared parameters'!$A$2:$A$200, MATCH($A10,'Shared parameters'!$B$2:$B$200,0) ), 'Data Entry'!$A$2:$B$200, 2, FALSE ), "") -> NA | C10: =IFERROR( VLOOKUP( INDEX('Shared parameters'!$A$2:$A$200, MATCH($A10,'Shared parameters'!$B$2:$B$200,0) ), 'Data Entry'!$A$2:$C$200, 3, FALSE ), "") -> — | D10: =IFERROR( VLOOKUP( INDEX('Shared parameters'!$A$2:$A$200, MATCH($A10,'Shared parameters'!$B$2:$B$200,0) ), 'Data Entry'!$A$2:$D$200, 4, FALSE ), "") -> NA
A11: =INDEX(SharedParams[Name],ROW(B10)) -> DPP_AUR_Supplier | B11: =IFERROR( VLOOKUP( INDEX('Shared parameters'!$A$2:$A$200, MATCH($A11,'Shared parameters'!$B$2:$B$200,0) ), 'Data Entry'!$A$2:$B$200, 2, FALSE ), "") -> NA | C11: =IFERROR( VLOOKUP( INDEX('Shared parameters'!$A$2:$A$200, MATCH($A11,'Shared parameters'!$B$2:$B$200,0) ), 'Data Entry'!$A$2:$C$200, 3, FALSE ), "") -> — | D11: =IFERROR( VLOOKUP( INDEX('Shared parameters'!$A$2:$A$200, MATCH($A11,'Shared parameters'!$B$2:$B$200,0) ), 'Data Entry'!$A$2:$D$200, 4, FALSE ), "") -> NA
A12: =INDEX(SharedParams[Name],ROW(B11)) -> DPP_AUR_Supplier_URL | B12: =IFERROR( VLOOKUP( INDEX('Shared parameters'!$A$2:$A$200, MATCH($A12,'Shared parameters'!$B$2:$B$200,0) ), 'Data Entry'!$A$2:$B$200, 2, FALSE ), "") -> NA | C12: =IFERROR( VLOOKUP( INDEX('Shared parameters'!$A$2:$A$200, MATCH($A12,'Shared parameters'!$B$2:$B$200,0) ), 'Data Entry'!$A$2:$C$200, 3, FALSE ), "") -> — | D12: =IFERROR( VLOOKUP( INDEX('Shared parameters'!$A$2:$A$200, MATCH($A12,'Shared parameters'!$B$2:$B$200,0) ), 'Data Entry'!$A$2:$D$200, 4, FALSE ), "") -> NA
A13: =INDEX(SharedParams[Name],ROW(B12)) -> DPP_AUT_TransRoute | B13: =IFERROR( VLOOKUP( INDEX('Shared parameters'!$A$2:$A$200, MATCH($A13,'Shared parameters'!$B$2:$B$200,0) ), 'Data Entry'!$A$2:$B$200, 2, FALSE ), "") -> 0 | C13: =IFERROR( VLOOKUP( INDEX('Shared parameters'!$A$2:$A$200, MATCH($A13,'Shared parameters'!$B$2:$B$200,0) ), 'Data Entry'!$A$2:$C$200, 3, FALSE ), "") -> 0 | D13: =IFERROR( VLOOKUP( INDEX('Shared parameters'!$A$2:$A$200, MATCH($A13,'Shared parameters'!$B$2:$B$200,0) ), 'Data Entry'!$A$2:$D$200, 4, FALSE ), "") -> 0
... A117: =INDEX(SharedParams[Name],ROW(B116)) -> DPP_COD_LCC_EUR | B117: =IFERROR( VLOOKUP( INDEX('Shared parameters'!$A$2:$A$200, MATCH($A117,'Shared parameters'!$B$2:$B$200,0) ), 'Data Entry'!$A$2:$B$200, 2, FALSE ), "") -> 47.376343 | C117: =IFERROR( VLOOKUP( INDEX('Shared parameters'!$A$2:$A$200, MATCH($A117,'Shared parameters'!$B$2:$B$200,0) ), 'Data Entry'!$A$2:$C$200, 3, FALSE ), "") -> €/m2 | D117: =IFERROR( VLOOKUP( INDEX('Shared parameters'!$A$2:$A$200, MATCH($A117,'Shared parameters'!$B$2:$B$200,0) ), 'Data Entry'!$A$2:$D$200, 4, FALSE ), "") -> 0
